[{"region": "CIALES", "area": "CIALES", "zone": "BO. HATO VIEJO"}, {"region": "CIALES", "area": "CIALES", "zone": "JAGUAS"}, {"region": "DORADO", "area": "DORADO", "zone": "DORADO DEL MAR"}, {"region": "DORADO", "area": "DORADO", "zone": "HACIENDAS DEL DORADO"}, {"region": "DORADO", "area": "DORADO", "zone": "HACIENDAS EL DORADO"}, {"region": "AGUAS BUENAS", "area": "AGUAS BUENAS", "zone": "URB SAN ANTONIO"}, {"region": "AIBONITO", "area": "AIBONITO", "zone": "ASOMANTE, LAS ABEJAS SOLAR 2"}, {"region": "AIBONITO", "area": "AIBONITO", "zone": "BO PASTO SECT PLAYITA"}, {"region": "AIBONITO", "area": "AIBONITO", "zone": "CASCO URBANO AIBONITO"}, {"region": "MOCA", "area": "MOCA", "zone": "BO CENTRO BZN 7973"}, {"region": "MOCA", "area": "MOCA", "zone": "BO ROCHA SEC CORTADERA 11540"}, {"region": "YABUCOA", "area": "YABUCOA", "zone": "GUAYABOTA                29053"}, {"region": "LARES", "area": "LARES", "zone": "BO. LARES"}, {"region": "LARES", "area": "LARES", "zone": "BO. PILETAS"}, {"region": "ARECIBO", "area": "ARECIBO", "zone": "BO. FACTOR 2"}, {"region": "ARECIBO", "area": "ARECIBO", "zone": "BO. RIO ARRIBA"}, {"region": "TOA ALTA", "area": "TOA ALTA", "zone": "BO RIO LAJAS SECT LOS RUFO"}, {"region": "TOA ALTA", "area": "TOA ALTA", "zone": "BO RIO LAJAS/SECT RUFO RDRGZ"}, {"region": "TOA ALTA", "area": "TOA ALTA", "zone": "BO RIO LAJASRUFO RODRIGUEZ"}, {"region": "TOA ALTA", "area": "TOA ALTA", "zone": "BO. QDA CRUZ"}, {"region": "TOA ALTA", "area": "TOA ALTA", "zone": "BO. QUEBRADA CRUZ"}, {"region": "TOA ALTA", "area": "TOA ALTA", "zone": "LA PROVIDENCIA"}, {"region": "TOA ALTA", "area": "TOA ALTA", "zone": "URB SAN FERNANDO"}, {"region": "LAJAS", "area": "LAJAS", "zone": "PAR OLIVARES 230"}, {"region": "SANTA ISABEL", "area": "SANTA ISABEL", "zone": "BO. JAUCA 2"}, {"region": "SAN SEBASTIAN", "area": "SAN SEBASTIAN", "zone": "BO. CIDRAL"}, {"region": "SAN SEBASTIAN", "area": "SAN SEBASTIAN", "zone": "BO. PERCHAS I"}, {"region": "SAN SEBASTIAN", "area": "SAN SEBASTIAN", "zone": "CALABAZAS   SECT  LOS PEREZ"}, {"region": "SAN SEBASTIAN", "area": "SAN SEBASTIAN", "zone": "SALTOS / LUIS RODRIGUEZ"}, {"region": "SAN SEBASTIAN", "area": "SAN SEBASTIAN", "zone": "SALTOS 2  SECT AGAPITO ROSADO"}, {"region": "SAN SEBASTIAN", "area": "SAN SEBASTIAN", "zone": "SALTOS I DESPUES GARAGE"}, {"region": "GUAYNABO", "area": "GUAYNABO", "zone": "BO STA ROSA NO 2"}, {"region": "GUAYNABO", "area": "GUAYNABO", "zone": "URB TORRIMAR"}, {"region": "JUNCOS", "area": "JUNCOS", "zone": "BO. VALENCIANO ABAJO"}, {"region": "CABO ROJO", "area": "CABO ROJO", "zone": "BO. BOQUER\u00d3N"}, {"region": "CABO ROJO", "area": "CABO ROJO", "zone": "BO. JOYUDAS"}, {"region": "CABO ROJO", "area": "CABO ROJO", "zone": "BO. PEDERNALES"}, {"region": "CABO ROJO", "area": "CABO ROJO", "zone": "CALLE LA MILAGROSA POLE OJEA"}, {"region": "CABO ROJO", "area": "CABO ROJO", "zone": "COND PASEOS DEL FARO"}, {"region": "CABO ROJO", "area": "CABO ROJO", "zone": "EL COMBATE"}, {"region": "CABO ROJO", "area": "CABO ROJO", "zone": "LLANOS COSTA"}, {"region": "CABO ROJO", "area": "CABO ROJO", "zone": "MONTE GRANDE"}, {"region": "CABO ROJO", "area": "CABO ROJO", "zone": "PAR BOQUERON"}, {"region": "CABO ROJO", "area": "CABO ROJO", "zone": "SECTOR CALLEJ\u00d3N MART\u00cdN"}, {"region": "CABO ROJO", "area": "CABO ROJO", "zone": "SECTOR COMBATE"}, {"region": "CABO ROJO", "area": "CABO ROJO", "zone": "SECTOR COROZO"}, {"region": "CABO ROJO", "area": "CABO ROJO", "zone": "URB ALTA VISTA SOLAR A"}, {"region": "CABO ROJO", "area": "CABO ROJO", "zone": "URB REPARTO SAMAN"}, {"region": "CAROLINA", "area": "CAROLINA", "zone": "URB JDNS COUNTRY CLUB"}, {"region": "TOA BAJA", "area": "TOA BAJA", "zone": "URB LEVITTOWN"}, {"region": "TOA BAJA", "area": "TOA BAJA", "zone": "URB LEVITTOWN*PEDESTAL EN 1563"}, {"region": "TOA BAJA", "area": "TOA BAJA", "zone": "URB. 2DA LEVITTOWN"}, {"region": "TOA BAJA", "area": "TOA BAJA", "zone": "URB. CAMPANERO"}, {"region": "BAYAMON", "area": "BAYAMON", "zone": "RIO PLANTATIONHATO TEJAS"}, {"region": "BAYAMON", "area": "BAYAMON", "zone": "URB FOREST VIEW"}, {"region": "BAYAMON", "area": "BAYAMON", "zone": "URB SANTA JUANITA"}, {"region": "GURABO", "area": "GURABO", "zone": "BO HATO NUEVO/COM MARIA JIMENE"}, {"region": "TRUJILLO ALTO", "area": "TRUJILLO ALTO", "zone": "BO QUEBRADA GRANDE/SECT ALAMO"}, {"region": "TRUJILLO ALTO", "area": "TRUJILLO ALTO", "zone": "BO. DOS BOCAS"}, {"region": "MANATI", "area": "MANATI", "zone": "BO MONTE BELLO"}, {"region": "MANATI", "area": "MANATI", "zone": "BO PUGNADO"}, {"region": "MANATI", "area": "MANATI", "zone": "BO. SABANA SECA"}, {"region": "MANATI", "area": "MANATI", "zone": "HOYOS MALO MONTEBELLO"}, {"region": "SAN JUAN", "area": "SAN JUAN", "zone": "BO. CUPEY BAJO"}, {"region": "SAN JUAN", "area": "SAN JUAN", "zone": "LA CUMBRE GARDENS"}, {"region": "SAN JUAN", "area": "SAN JUAN", "zone": "MARACAY TOWNHOUSES"}, {"region": "SAN JUAN", "area": "SAN JUAN", "zone": "URB RIVIERAS DE CUPEY"}, {"region": "SAN JUAN", "area": "SAN JUAN", "zone": "URB ROOSEVELT"}, {"region": "CAGUAS", "area": "CAGUAS", "zone": "BAIROA GOLDEN GATE"}, {"region": "CAGUAS", "area": "CAGUAS", "zone": "BORINQUEN SECTOR EL PADRE"}, {"region": "CAGUAS", "area": "CAGUAS", "zone": "MALL COMMUNITY SHOPPING CENTER"}, {"region": "CAGUAS", "area": "CAGUAS", "zone": "URB JOSE M DELGADO"}, {"region": "CEIBA", "area": "CEIBA", "zone": "CEIBA"}, {"region": "CEIBA", "area": "CEIBA", "zone": "URB JARD DE CEIBA"}, {"region": "CEIBA", "area": "CEIBA", "zone": "URB VALLE DE CEIBA II"}, {"region": "CEIBA", "area": "CEIBA", "zone": "URB. HACIENDA LAS LOMAS"}, {"region": "MOROVIS", "area": "MOROVIS", "zone": "BO FRANQUEZ"}, {"region": "NARANJITO", "area": "NARANJITO", "zone": "BO CEDRO ABAJO"}, {"region": "NARANJITO", "area": "NARANJITO", "zone": "BO LOMAS CUCHILLA"}, {"region": "VEGA BAJA", "area": "VEGA BAJA", "zone": "BDA. SANTA ROSA"}, {"region": "VEGA BAJA", "area": "VEGA BAJA", "zone": "BO ALM NOR SEC EL INDIO"}, {"region": "VEGA BAJA", "area": "VEGA BAJA", "zone": "RIO ABAJO 1ER.NIVEL"}, {"region": "SAN LORENZO", "area": "SAN LORENZO", "zone": "URB LOS TAMARINDOS"}]