[{"region": "COROZAL", "area": "COROZAL", "zone": "BO DOS BOCAS I  PARC.ORTIZ"}, {"region": "COROZAL", "area": "COROZAL", "zone": "URB MARIA DEL CARMEN"}, {"region": "CIALES", "area": "CIALES", "zone": "BO POZAS - ENT DER.DESP MECANI"}, {"region": "CIALES", "area": "CIALES", "zone": "Bo. Toro Negro"}, {"region": "CIALES", "area": "CIALES", "zone": "CIALITOS"}, {"region": "CIALES", "area": "CIALES", "zone": "FRONTON"}, {"region": "PATILLAS", "area": "PATILLAS", "zone": "URB VALLES DE PATILLAS"}, {"region": "HATILLO", "area": "HATILLO", "zone": "BO CAPAEZ"}, {"region": "GUAYANILLA", "area": "GUAYANILLA", "zone": "BO SIERRA BAJA"}, {"region": "AGUAS BUENAS", "area": "AGUAS BUENAS", "zone": "JAGUEYES/LOS BRUNOS/CAPO"}, {"region": "RIO GRANDE", "area": "RIO GRANDE", "zone": "Bo. Malpica"}, {"region": "RIO GRANDE", "area": "RIO GRANDE", "zone": "LAS 3 T  HACIENDA JIMENEZ"}, {"region": "RIO GRANDE", "area": "RIO GRANDE", "zone": "URB VISTAS RIO GRANDE II"}, {"region": "VEGA ALTA", "area": "VEGA ALTA", "zone": "n/a"}, {"region": "AIBONITO", "area": "AIBONITO", "zone": "BO. RABANAL LA SIERRA"}, {"region": "RINCON", "area": "RINCON", "zone": "BO PUNTAS"}, {"region": "YABUCOA", "area": "YABUCOA", "zone": "BO GUAYABOTAS SEC LAS PANAS"}, {"region": "JUANA DIAZ", "area": "JUANA DIAZ", "zone": "BO SINGAPUR"}, {"region": "JUANA DIAZ", "area": "JUANA DIAZ", "zone": "GUAYABAL"}, {"region": "OROCOVIS", "area": "OROCOVIS", "zone": "BO BAUTA ABAJO SEC LA FRANCIA"}, {"region": "OROCOVIS", "area": "OROCOVIS", "zone": "BO BOTIJAS II-SECT LAS MARIAS"}, {"region": "OROCOVIS", "area": "OROCOVIS", "zone": "BO SALTOSCOLI SEC MIRAFLORES"}, {"region": "ARECIBO", "area": "ARECIBO", "zone": "URB LUGARDO NO 6"}, {"region": "SABANA GRANDE", "area": "SABANA GRANDE", "zone": "Bo. Susua"}, {"region": "SALINAS", "area": "SALINAS", "zone": "BO MONTE GRANDE"}, {"region": "SALINAS", "area": "SALINAS", "zone": "EXT COQUI LOS SOLARES AGUIRRE"}, {"region": "HORMIGUEROS", "area": "HORMIGUEROS", "zone": "HACIENDA CONSTANCIA"}, {"region": "QUEBRADILLAS", "area": "QUEBRADILLAS", "zone": "SAN JOSE CJN LOS PERROS"}, {"region": "GUAYNABO", "area": "GUAYNABO", "zone": "ALTO APOLO ESTATES"}, {"region": "GUAYNABO", "area": "GUAYNABO", "zone": "SECTOR LA MUDA"}, {"region": "GUAYNABO", "area": "GUAYNABO", "zone": "URB GARDEN HILLS"}, {"region": "GUAYNABO", "area": "GUAYNABO", "zone": "URB PUB JUAN GARCIA DUCOS"}, {"region": "PENUELAS", "area": "PENUELAS", "zone": "AAA-EBA,BACO"}, {"region": "PENUELAS", "area": "PENUELAS", "zone": "BO COTO QUEBRADAS"}, {"region": "CAROLINA", "area": "CAROLINA", "zone": "BARRAZAS ARRAYANES"}, {"region": "CAROLINA", "area": "CAROLINA", "zone": "Bo. Cedros"}, {"region": "CAROLINA", "area": "CAROLINA", "zone": "SABANA ABAJO"}, {"region": "ADJUNTAS", "area": "ADJUNTAS", "zone": "BO JUAN GONZALEZ"}, {"region": "ADJUNTAS", "area": "ADJUNTAS", "zone": "Bo. Tanama"}, {"region": "ADJUNTAS", "area": "ADJUNTAS", "zone": "Bo. Vegas Abajo"}, {"region": "SAN GERMAN", "area": "SAN GERMAN", "zone": "BO HOCONUCO BAJO"}, {"region": "SAN GERMAN", "area": "SAN GERMAN", "zone": "Bo. Rosario Bajo"}, {"region": "BAYAMON", "area": "BAYAMON", "zone": "BO GUARAGUAO ARRIBA"}, {"region": "BAYAMON", "area": "BAYAMON", "zone": "GUARAGUAO ARRIBA"}, {"region": "BAYAMON", "area": "BAYAMON", "zone": "URB AGUSTIN STAHL"}, {"region": "BAYAMON", "area": "BAYAMON", "zone": "URB FLAMBOYAN GARDENS"}, {"region": "CANOVANAS", "area": "CANOVANAS", "zone": "BO CUBUY"}, {"region": "CANOVANAS", "area": "CANOVANAS", "zone": "CANOVANAS"}, {"region": "CANOVANAS", "area": "CANOVANAS", "zone": "URB ESTANCIAS DEL RIO"}, {"region": "CANOVANAS", "area": "CANOVANAS", "zone": "URB RIVER PLANTATION"}, {"region": "VILLALBA", "area": "VILLALBA", "zone": "BO JAGUEYES/LAO BRAVO"}, {"region": "VILLALBA", "area": "VILLALBA", "zone": "HATO PUERCO ARRIBA"}, {"region": "GURABO", "area": "GURABO", "zone": "CELADA"}, {"region": "GURABO", "area": "GURABO", "zone": "HATO NUEVO"}, {"region": "GURABO", "area": "GURABO", "zone": "NAVARRO"}, {"region": "MARICAO", "area": "MARICAO", "zone": "BO BUCARABONES"}, {"region": "MARICAO", "area": "MARICAO", "zone": "INDIERA FRIA SECT LAS PIEDRAS"}, {"region": "TRUJILLO ALTO", "area": "TRUJILLO ALTO", "zone": "ANTIGUA VIA"}, {"region": "TRUJILLO ALTO", "area": "TRUJILLO ALTO", "zone": "BO CARRAIZO ALTO"}, {"region": "TRUJILLO ALTO", "area": "TRUJILLO ALTO", "zone": "COND CAMINO TERRA VERDE"}, {"region": "TRUJILLO ALTO", "area": "TRUJILLO ALTO", "zone": "SECTOR SABANA BO QDA GRANDE"}, {"region": "PONCE", "area": "PONCE", "zone": "BO MAGUEYES"}, {"region": "PONCE", "area": "PONCE", "zone": "COTO LAUREL"}, {"region": "PONCE", "area": "PONCE", "zone": "MACHUELO ABAJO"}, {"region": "PONCE", "area": "PONCE", "zone": "URB GRANADA HILLS"}, {"region": "JAYUYA", "area": "JAYUYA", "zone": "BO VEGUITA ZAMAS PUERTO PLATA"}, {"region": "JAYUYA", "area": "JAYUYA", "zone": "BO ZAMASSECT LOS ORTIZES"}, {"region": "CAYEY", "area": "CAYEY", "zone": "BO LA PIEDRA SECT LA PIEDRA"}, {"region": "COAMO", "area": "COAMO", "zone": "BO CUYON/PARCELAS NUEVAS"}, {"region": "NAGUABO", "area": "NAGUABO", "zone": "BO MARIANA            RL-27034"}, {"region": "SAN JUAN", "area": "SAN JUAN", "zone": "QUEBRADA ARENAS"}, {"region": "SAN JUAN", "area": "SAN JUAN", "zone": "SABANA LLANA NORTE"}, {"region": "SAN JUAN", "area": "SAN JUAN", "zone": "URB CAPARRA HEIGHTS"}, {"region": "SAN JUAN", "area": "SAN JUAN", "zone": "URB CAPARRA TERRACE"}, {"region": "SAN JUAN", "area": "SAN JUAN", "zone": "URB COUNTRY CLUB"}, {"region": "SAN JUAN", "area": "SAN JUAN", "zone": "URB MONTECARLO"}, {"region": "SAN JUAN", "area": "SAN JUAN", "zone": "URB PUERTO NUEVO"}, {"region": "SAN JUAN", "area": "SAN JUAN", "zone": "URB SAN AGUSTIN"}, {"region": "SAN JUAN", "area": "SAN JUAN", "zone": "Urb. Villa Prades"}, {"region": "CAGUAS", "area": "CAGUAS", "zone": "Bo. Borinquen"}, {"region": "CAGUAS", "area": "CAGUAS", "zone": "TOMAS DE CASTRO NUM.1"}, {"region": "CAGUAS", "area": "CAGUAS", "zone": "URB PARQUE LAS MERCEDES"}, {"region": "CAGUAS", "area": "CAGUAS", "zone": "VILLA BLANCA"}, {"region": "MOROVIS", "area": "MOROVIS", "zone": "BO PASTOS"}, {"region": "NARANJITO", "area": "NARANJITO", "zone": "BO CEDRO ABAJO-SECT CIELITO"}, {"region": "NARANJITO", "area": "NARANJITO", "zone": "BO NUEVO"}, {"region": "NARANJITO", "area": "NARANJITO", "zone": "LOMAS VALLES"}, {"region": "NARANJITO", "area": "NARANJITO", "zone": "Sector Higuillares"}, {"region": "NARANJITO", "area": "NARANJITO", "zone": "Sector Lomas Jaguas"}, {"region": "SAN LORENZO", "area": "SAN LORENZO", "zone": "BO QUEMADO /COLINAS DE QUEMADO"}, {"region": "MAYAGUEZ", "area": "MAYAGUEZ", "zone": "BO MALEZAS"}, {"region": "MAYAGUEZ", "area": "MAYAGUEZ", "zone": "CMNO DONA LALA BO BATEYES"}, {"region": "MAYAGUEZ", "area": "MAYAGUEZ", "zone": "PARCELAS ROLON CASA 120"}, {"region": "MAYAGUEZ", "area": "MAYAGUEZ", "zone": "Urb. Altura De Mayag\u00fce"}, {"region": "YAUCO", "area": "YAUCO", "zone": "AGUAS BLANCAS"}, {"region": "YAUCO", "area": "YAUCO", "zone": "BO ALGARROBO PUENTE EL AJI"}, {"region": "YAUCO", "area": "YAUCO", "zone": "BO QUEBRADAS DONA TITO"}, {"region": "YAUCO", "area": "YAUCO", "zone": "SECTOR CANGREJOS"}]