[{"region": "GUAYAMA", "area": "GUAYAMA", "zone": "PLAYITA MACHETE"}, {"region": "HATILLO", "area": "HATILLO", "zone": "BO CARRIZALES - LAS CANELAS"}, {"region": "HATILLO", "area": "HATILLO", "zone": "Bo. Carrizalez"}, {"region": "HATILLO", "area": "HATILLO", "zone": "CORCOVADO"}, {"region": "HATILLO", "area": "HATILLO", "zone": "Casco Urbano de Hatillo"}, {"region": "GUAYANILLA", "area": "GUAYANILLA", "zone": "Bo. Quebrada Honda"}, {"region": "AGUAS BUENAS", "area": "AGUAS BUENAS", "zone": "Bo. Mulas"}, {"region": "AGUAS BUENAS", "area": "AGUAS BUENAS", "zone": "n/a"}, {"region": "AIBONITO", "area": "AIBONITO", "zone": "Bo. Caonillas"}, {"region": "RINCON", "area": "RINCON", "zone": "BO RIO GRANDE LOMA LOS GAVILAN"}, {"region": "RINCON", "area": "RINCON", "zone": "Bo. Puntas"}, {"region": "ANASCO", "area": "ANASCO", "zone": "Bo. Espino"}, {"region": "ANASCO", "area": "ANASCO", "zone": "Bo. Hatillo"}, {"region": "ANASCO", "area": "ANASCO", "zone": "Bo. Miraflores"}, {"region": "CIDRA", "area": "CIDRA", "zone": "BO HONDURAS- FILEMON"}, {"region": "CIDRA", "area": "CIDRA", "zone": "Bo. Ceiba"}, {"region": "CIDRA", "area": "CIDRA", "zone": "Bo. Rabanal"}, {"region": "CIDRA", "area": "CIDRA", "zone": "Bo. Toita"}, {"region": "CIDRA", "area": "CIDRA", "zone": "RABANAL"}, {"region": "MOCA", "area": "MOCA", "zone": "Bo. Cerro Gordo"}, {"region": "YABUCOA", "area": "YABUCOA", "zone": "CALABAZAS   SODOMA       29062"}, {"region": "LARES", "area": "LARES", "zone": "BO MIRASOL"}, {"region": "OROCOVIS", "area": "OROCOVIS", "zone": "Bo. Damian Arriba"}, {"region": "ARECIBO", "area": "ARECIBO", "zone": "BO. HATO VIEJO"}, {"region": "ARECIBO", "area": "ARECIBO", "zone": "ESPERANZA"}, {"region": "ARECIBO", "area": "ARECIBO", "zone": "PARCELAS ISLOTE 2 PAR 413"}, {"region": "ARECIBO", "area": "ARECIBO", "zone": "SABANA HOYOS"}, {"region": "TOA ALTA", "area": "TOA ALTA", "zone": "GALATEO CENTRO"}, {"region": "SABANA GRANDE", "area": "SABANA GRANDE", "zone": "BO RAYO LOS HORNOS"}, {"region": "SABANA GRANDE", "area": "SABANA GRANDE", "zone": "Bo. Molinas"}, {"region": "SABANA GRANDE", "area": "SABANA GRANDE", "zone": "Bo. Rayo Plata"}, {"region": "ISABELA", "area": "ISABELA", "zone": "BO. LLANADAS"}, {"region": "ISABELA", "area": "ISABELA", "zone": "n/a"}, {"region": "HORMIGUEROS", "area": "HORMIGUEROS", "zone": "CENTRO COMERCIAL MAYAG"}, {"region": "AGUADILLA", "area": "AGUADILLA", "zone": "CASA 135 BUZON 148"}, {"region": "AGUADILLA", "area": "AGUADILLA", "zone": "URB QUINTAS DE SAN JOSE"}, {"region": "AGUADILLA", "area": "AGUADILLA", "zone": "Urb. Marbella"}, {"region": "GUAYNABO", "area": "GUAYNABO", "zone": "Bo. Frailes"}, {"region": "GUAYNABO", "area": "GUAYNABO", "zone": "Bo. Rio"}, {"region": "GUAYNABO", "area": "GUAYNABO", "zone": "Casco Urbano Guaynabo"}, {"region": "GUAYNABO", "area": "GUAYNABO", "zone": "FRAILES"}, {"region": "GUAYNABO", "area": "GUAYNABO", "zone": "MAMEY 2"}, {"region": "GUAYNABO", "area": "GUAYNABO", "zone": "TORRIMAR FTE COL MARISTA GUAYN"}, {"region": "GUAYNABO", "area": "GUAYNABO", "zone": "URB. LA VILLA DE TORRIMAR"}, {"region": "JUNCOS", "area": "JUNCOS", "zone": "ESTANCIAS DE JUNCOS/BO MANGO"}, {"region": "JUNCOS", "area": "JUNCOS", "zone": "JARDINES DE BARCELONA R-081"}, {"region": "CABO ROJO", "area": "CABO ROJO", "zone": "BO LLANOS TUNA"}, {"region": "CABO ROJO", "area": "CABO ROJO", "zone": "BO MIRADERO  PARABUEYON"}, {"region": "CABO ROJO", "area": "CABO ROJO", "zone": "Bo. Cerrillos"}, {"region": "CABO ROJO", "area": "CABO ROJO", "zone": "TERRAZAS DE BOQUERON"}, {"region": "CABO ROJO", "area": "CABO ROJO", "zone": "URB MONTE REAL"}, {"region": "CABO ROJO", "area": "CABO ROJO", "zone": "URB VEREDAS DEL MAR BO MIRADERO"}, {"region": "CABO ROJO", "area": "CABO ROJO", "zone": "URB VISTA VERDE"}, {"region": "PENUELAS", "area": "PENUELAS", "zone": "BO TALLABOA/SEC SEBORUCO"}, {"region": "PENUELAS", "area": "PENUELAS", "zone": "n/a"}, {"region": "ADJUNTAS", "area": "ADJUNTAS", "zone": "BO YAYALES"}, {"region": "ADJUNTAS", "area": "ADJUNTAS", "zone": "Bo. Limani"}, {"region": "SAN GERMAN", "area": "SAN GERMAN", "zone": "BO. MARESUA"}, {"region": "SAN GERMAN", "area": "SAN GERMAN", "zone": "Bo. Cain Bajo"}, {"region": "SAN GERMAN", "area": "SAN GERMAN", "zone": "Bo. Duey Alto"}, {"region": "SAN GERMAN", "area": "SAN GERMAN", "zone": "Bo. Rosario Penon"}, {"region": "SAN GERMAN", "area": "SAN GERMAN", "zone": "ROSARIO ALTO"}, {"region": "SAN GERMAN", "area": "SAN GERMAN", "zone": "ROSARIO ALTO,SECTOR BALLESTER"}, {"region": "SAN GERMAN", "area": "SAN GERMAN", "zone": "ROSARIO ANTES DE JOSE IRIZARRY"}, {"region": "SAN GERMAN", "area": "SAN GERMAN", "zone": "SECTOR LA TEA"}, {"region": "BAYAMON", "area": "BAYAMON", "zone": "Bo. Juan Sanchez"}, {"region": "BAYAMON", "area": "BAYAMON", "zone": "MINILLAS"}, {"region": "BAYAMON", "area": "BAYAMON", "zone": "SECTOR MONTE LLANOS"}, {"region": "ARROYO", "area": "ARROYO", "zone": "URB QUINTAS DE GUASIMAS"}, {"region": "CANOVANAS", "area": "CANOVANAS", "zone": "Bo. San Isidro"}, {"region": "GURABO", "area": "GURABO", "zone": "BO. MASSAS I/SECT EL SILENCIO"}, {"region": "GURABO", "area": "GURABO", "zone": "BO. NAVARRO"}, {"region": "MARICAO", "area": "MARICAO", "zone": "Bo. Indiera Baja"}, {"region": "MARICAO", "area": "MARICAO", "zone": "Bo. Indiera Fria"}, {"region": "MARICAO", "area": "MARICAO", "zone": "Sector La Aceituna"}, {"region": "LAS PIEDRAS", "area": "LAS PIEDRAS", "zone": "MANSIONES DE LOS ARTESANOS"}, {"region": "TRUJILLO ALTO", "area": "TRUJILLO ALTO", "zone": "INTERAMERICANA GDNS APTS"}, {"region": "CAMUY", "area": "CAMUY", "zone": "BO MEMBRILLO/VISTA LOS PENONES"}, {"region": "CAMUY", "area": "CAMUY", "zone": "BO ZANJAS"}, {"region": "CAMUY", "area": "CAMUY", "zone": "ZANJAS/VIEQUES"}, {"region": "PONCE", "area": "PONCE", "zone": "Bo. Buyones"}, {"region": "PONCE", "area": "PONCE", "zone": "Bo. Guaraguao"}, {"region": "PONCE", "area": "PONCE", "zone": "Bo. Real Anon"}, {"region": "JAYUYA", "area": "JAYUYA", "zone": "BARRIO ZAMAS"}, {"region": "JAYUYA", "area": "JAYUYA", "zone": "Bo. Mameyes Arriba"}, {"region": "JAYUYA", "area": "JAYUYA", "zone": "MAMEYES ARRIBA"}, {"region": "JAYUYA", "area": "JAYUYA", "zone": "PAR SANTA BARBARA"}, {"region": "CAYEY", "area": "CAYEY", "zone": "ALTURAS DE BEATRIZ"}, {"region": "CAYEY", "area": "CAYEY", "zone": "Bo. Beatriz"}, {"region": "CAYEY", "area": "CAYEY", "zone": "VILLAS DE JOHNNY TOLEDO"}, {"region": "SAN JUAN", "area": "SAN JUAN", "zone": "Ave. Am\u00e9rico Miranda"}, {"region": "SAN JUAN", "area": "SAN JUAN", "zone": "Ave. Munoz RIvera"}, {"region": "SAN JUAN", "area": "SAN JUAN", "zone": "CAPARRA TERRACE"}, {"region": "SAN JUAN", "area": "SAN JUAN", "zone": "COND ASTOR URB PUERTO NUEVO"}, {"region": "SAN JUAN", "area": "SAN JUAN", "zone": "COND LOS NARDOS"}, {"region": "SAN JUAN", "area": "SAN JUAN", "zone": "CUPEY"}, {"region": "SAN JUAN", "area": "SAN JUAN", "zone": "CUPEY ALTO  LOS CONDES"}, {"region": "SAN JUAN", "area": "SAN JUAN", "zone": "REPTO UNIVERSITARIO"}, {"region": "SAN JUAN", "area": "SAN JUAN", "zone": "Res. San Juan Bautista"}, {"region": "SAN JUAN", "area": "SAN JUAN", "zone": "URB SAN IGNACIO"}, {"region": "SAN JUAN", "area": "SAN JUAN", "zone": "VISTAS DEL HORIZONTE II"}, {"region": "GUANICA", "area": "GUANICA", "zone": "BDA ESPERANZA"}, {"region": "GUANICA", "area": "GUANICA", "zone": "Bo. Fuig"}, {"region": "GUANICA", "area": "GUANICA", "zone": "PISO 2,BRISAS DE TORTUGUERO"}, {"region": "GUANICA", "area": "GUANICA", "zone": "Urb. Vista Mar"}, {"region": "CAGUAS", "area": "CAGUAS", "zone": "BO BEATRIZ/SECT PINA/RTA 476"}, {"region": "CAGUAS", "area": "CAGUAS", "zone": "BO CANABONCITO"}, {"region": "CAGUAS", "area": "CAGUAS", "zone": "Bo. Canabon"}, {"region": "CAGUAS", "area": "CAGUAS", "zone": "LAKEVIEW DRIVE"}, {"region": "MOROVIS", "area": "MOROVIS", "zone": "Bo. Unibon"}, {"region": "MOROVIS", "area": "MOROVIS", "zone": "UNIBON"}, {"region": "SAN LORENZO", "area": "SAN LORENZO", "zone": "BO QDA ARENAS REMOTO F"}, {"region": "MAYAGUEZ", "area": "MAYAGUEZ", "zone": "BARRIO BALBOA"}, {"region": "MAYAGUEZ", "area": "MAYAGUEZ", "zone": "BO CAMBALACHE"}, {"region": "MAYAGUEZ", "area": "MAYAGUEZ", "zone": "BO RIO CANAS ABAJO"}, {"region": "MAYAGUEZ", "area": "MAYAGUEZ", "zone": "BO RIO CANAS ARRIBA"}, {"region": "MAYAGUEZ", "area": "MAYAGUEZ", "zone": "BO. QUEMADO CAM RATE DESARDEN"}, {"region": "MAYAGUEZ", "area": "MAYAGUEZ", "zone": "Bo. Limon"}, {"region": "MAYAGUEZ", "area": "MAYAGUEZ", "zone": "Bo. Miradero"}, {"region": "MAYAGUEZ", "area": "MAYAGUEZ", "zone": "Bo. Paris"}, {"region": "MAYAGUEZ", "area": "MAYAGUEZ", "zone": "Bo. Quemado"}, {"region": "MAYAGUEZ", "area": "MAYAGUEZ", "zone": "Casco Urbano Mayag\u00fcez"}, {"region": "MAYAGUEZ", "area": "MAYAGUEZ", "zone": "JUAN ALONSO"}, {"region": "MAYAGUEZ", "area": "MAYAGUEZ", "zone": "MAYAGUEZ ARRIBA"}, {"region": "MAYAGUEZ", "area": "MAYAGUEZ", "zone": "RES ARBOLEDA"}, {"region": "MAYAGUEZ", "area": "MAYAGUEZ", "zone": "SECTOR LA QUINTA"}, {"region": "MAYAGUEZ", "area": "MAYAGUEZ", "zone": "Sector Rio Canas Arrib"}, {"region": "MAYAGUEZ", "area": "MAYAGUEZ", "zone": "URB SULTANA"}, {"region": "YAUCO", "area": "YAUCO", "zone": "Bo. Aguas Blancas"}, {"region": "YAUCO", "area": "YAUCO", "zone": "Bo. Algarrobo"}, {"region": "YAUCO", "area": "YAUCO", "zone": "Bo. Duey"}, {"region": "YAUCO", "area": "YAUCO", "zone": "Bo. Rio Prieto"}, {"region": "YAUCO", "area": "YAUCO", "zone": "Bo. Sierra Alta"}, {"region": "YAUCO", "area": "YAUCO", "zone": "DUEY"}, {"region": "YAUCO", "area": "YAUCO", "zone": "SUSUA BAJA"}, {"region": "YAUCO", "area": "YAUCO", "zone": "URB EL CAFETAL"}]