[{"region": "CIALES", "area": "CIALES", "zone": "BZ 6248 POZA MANICABOA"}, {"region": "LAS MARIAS", "area": "LAS MARIAS", "zone": "BO. CERROTE"}, {"region": "LAS MARIAS", "area": "LAS MARIAS", "zone": "MARAVILLA ESTE"}, {"region": "PATILLAS", "area": "PATILLAS", "zone": "BO. GUARDARRAYA"}, {"region": "GUAYAMA", "area": "GUAYAMA", "zone": "URB ESTANCIAS DE DULCE SUE\u00d1O"}, {"region": "GUAYANILLA", "area": "GUAYANILLA", "zone": "BO. QUEBRADAS"}, {"region": "AGUAS BUENAS", "area": "AGUAS BUENAS", "zone": "BO. MULAS"}, {"region": "HUMACAO", "area": "HUMACAO", "zone": "URB. PALMAS DEL MAR"}, {"region": "FLORIDA", "area": "FLORIDA", "zone": "BO FLORIDA/BEJUCO"}, {"region": "RIO GRANDE", "area": "RIO GRANDE", "zone": "URB. RIO GRANDE STATES"}, {"region": "VEGA ALTA", "area": "VEGA ALTA", "zone": "BO MARICAO SECTOR EL 9"}, {"region": "VEGA ALTA", "area": "VEGA ALTA", "zone": "ZONA URBANA VEGA ALTA"}, {"region": "MOCA", "area": "MOCA", "zone": "BO ROCHA"}, {"region": "YABUCOA", "area": "YABUCOA", "zone": "BO QUEBRADILLAS, R29038"}, {"region": "ARECIBO", "area": "ARECIBO", "zone": "BO QUEBRADA"}, {"region": "ARECIBO", "area": "ARECIBO", "zone": "HATO ABAJO"}, {"region": "ARECIBO", "area": "ARECIBO", "zone": "HATO ABAJOBARRANCA"}, {"region": "QUEBRADILLAS", "area": "QUEBRADILLAS", "zone": "BO COCOS"}, {"region": "QUEBRADILLAS", "area": "QUEBRADILLAS", "zone": "BO COCOS EL VERDE"}, {"region": "QUEBRADILLAS", "area": "QUEBRADILLAS", "zone": "BO SAN JOSE SECTOR JAYUYA"}, {"region": "CABO ROJO", "area": "CABO ROJO", "zone": "URB. ALTURAS DE JOYUDA"}, {"region": "CAROLINA", "area": "CAROLINA", "zone": "SECTOR JULIA DE BURGOS"}, {"region": "BARRANQUITAS", "area": "BARRANQUITAS", "zone": "BARRANCAS"}, {"region": "BAYAMON", "area": "BAYAMON", "zone": "HATO TEJAS"}, {"region": "BAYAMON", "area": "BAYAMON", "zone": "URB RIVERVIEW"}, {"region": "MARICAO", "area": "MARICAO", "zone": "BO. BUCARABONES"}, {"region": "TRUJILLO ALTO", "area": "TRUJILLO ALTO", "zone": "BO. CARRAIZO"}, {"region": "TRUJILLO ALTO", "area": "TRUJILLO ALTO", "zone": "QUEBRADA GRANDE"}, {"region": "CAMUY", "area": "CAMUY", "zone": "BO QUEBRADA"}, {"region": "JAYUYA", "area": "JAYUYA", "zone": "BO. VEGUITA"}, {"region": "CAYEY", "area": "CAYEY", "zone": "CAYEY LIQUOR STORE"}, {"region": "MANATI", "area": "MANATI", "zone": "COTO NORTE"}, {"region": "SAN JUAN", "area": "SAN JUAN", "zone": "ALTURAS DE FAIR VIEW"}, {"region": "SAN JUAN", "area": "SAN JUAN", "zone": "BO OBRERO"}, {"region": "SAN JUAN", "area": "SAN JUAN", "zone": "PARADA 27"}, {"region": "SAN JUAN", "area": "SAN JUAN", "zone": "URB CAPARRA TERRACE"}, {"region": "SAN JUAN", "area": "SAN JUAN", "zone": "URB LA CUMBRE"}, {"region": "SAN JUAN", "area": "SAN JUAN", "zone": "URB PINERO"}, {"region": "CAGUAS", "area": "CAGUAS", "zone": "BONNEVILLE TERRACE"}, {"region": "CAGUAS", "area": "CAGUAS", "zone": "URB BONNEVILLE MANORS"}, {"region": "CAGUAS", "area": "CAGUAS", "zone": "URB VILLA TURABOACCESO"}, {"region": "VEGA BAJA", "area": "VEGA BAJA", "zone": "BO. ALGARROBO"}]