[{"region": "DORADO", "area": "DORADO", "zone": "MAGUAYO URB GOLDEN HILLS"}, {"region": "HATILLO", "area": "HATILLO", "zone": "BO. PUEBLO"}, {"region": "HUMACAO", "area": "HUMACAO", "zone": "COLLORES LOS CATALANES 26032"}, {"region": "LOIZA", "area": "LOIZA", "zone": "BO MINIMINI"}, {"region": "COMERIO", "area": "COMERIO", "zone": "BO RIO HONDO"}, {"region": "COMERIO", "area": "COMERIO", "zone": "RIO HONDO"}, {"region": "VEGA ALTA", "area": "VEGA ALTA", "zone": "BO. CIENEGUETA"}, {"region": "YABUCOA", "area": "YABUCOA", "zone": "PAR COMUNA-CALAMBRENA-GANDULAR"}, {"region": "ARECIBO", "area": "ARECIBO", "zone": "SEC CANINA BO RIO ARRIBA"}, {"region": "ISABELA", "area": "ISABELA", "zone": "BO GUERRERO REPTO YOMAIRA"}, {"region": "SAN SEBASTIAN", "area": "SAN SEBASTIAN", "zone": "BO. CIDRAL"}, {"region": "QUEBRADILLAS", "area": "QUEBRADILLAS", "zone": "BO. SAN ANTONIO"}, {"region": "GUAYNABO", "area": "GUAYNABO", "zone": "BO. SANTA ROSA"}, {"region": "JUNCOS", "area": "JUNCOS", "zone": "CEIBA NORTE"}, {"region": "CABO ROJO", "area": "CABO ROJO", "zone": "MIRADERO"}, {"region": "CAROLINA", "area": "CAROLINA", "zone": "BO. CEDROS"}, {"region": "CAROLINA", "area": "CAROLINA", "zone": "SAN ANTON"}, {"region": "CAROLINA", "area": "CAROLINA", "zone": "URB METROPOLIS"}, {"region": "CAROLINA", "area": "CAROLINA", "zone": "URB VALLE ARRIBA HEIGHTS"}, {"region": "BARRANQUITAS", "area": "BARRANQUITAS", "zone": "BDA LA VEGA"}, {"region": "SAN GERMAN", "area": "SAN GERMAN", "zone": "BO HOCONUCO MILLAN"}, {"region": "SAN GERMAN", "area": "SAN GERMAN", "zone": "RES EL RECREO"}, {"region": "BAYAMON", "area": "BAYAMON", "zone": "CASCO URBANO BAYAM\u00d3N"}, {"region": "BAYAMON", "area": "BAYAMON", "zone": "LA MORENITA BO GUARAGUAO"}, {"region": "BAYAMON", "area": "BAYAMON", "zone": "VAN SCOY BUENA VISTA"}, {"region": "CANOVANAS", "area": "CANOVANAS", "zone": "BO. CUBUY"}, {"region": "CANOVANAS", "area": "CANOVANAS", "zone": "BO. LOMAS"}, {"region": "CANOVANAS", "area": "CANOVANAS", "zone": "LOMAS"}, {"region": "VILLALBA", "area": "VILLALBA", "zone": "BO CAMARONES ARRIBA"}, {"region": "MANATI", "area": "MANATI", "zone": "BO GUAYANEY SEC ERNESTO ROSADO"}, {"region": "MANATI", "area": "MANATI", "zone": "BO. GUAYANEY"}, {"region": "MANATI", "area": "MANATI", "zone": "COTO NORTE"}, {"region": "SAN JUAN", "area": "SAN JUAN", "zone": "BO. CUPEY ALTO"}, {"region": "SAN JUAN", "area": "SAN JUAN", "zone": "HATO REY P R"}, {"region": "SAN JUAN", "area": "SAN JUAN", "zone": "URB PUERTO NUEVO"}, {"region": "CAGUAS", "area": "CAGUAS", "zone": "PAR LAS CAROLINAS"}, {"region": "CAGUAS", "area": "CAGUAS", "zone": "URB NOTRE DAME"}, {"region": "CAGUAS", "area": "CAGUAS", "zone": "URB. NOTRE DAME"}, {"region": "CAGUAS", "area": "CAGUAS", "zone": "VILLA NUEVA"}]