[{"region": "LAS MARIAS", "area": "LAS MARIAS", "zone": "Bo. Buena Vista"}, {"region": "PATILLAS", "area": "PATILLAS", "zone": "BO BAJOS/BARRO BLANCO AL FINAL"}, {"region": "PATILLAS", "area": "PATILLAS", "zone": "BO MARIN ALTO SECTOR EGOSCUE"}, {"region": "GUAYAMA", "area": "GUAYAMA", "zone": "BO CARITE SECTOR EL LAGO"}, {"region": "GUAYAMA", "area": "GUAYAMA", "zone": "Bo. Carite"}, {"region": "BARCELONETA", "area": "BARCELONETA", "zone": "PAR PALENQUE NUM 36"}, {"region": "BARCELONETA", "area": "BARCELONETA", "zone": "URB ISLA ROQUE ESTATES"}, {"region": "HUMACAO", "area": "HUMACAO", "zone": "PLAYA"}, {"region": "VEGA ALTA", "area": "VEGA ALTA", "zone": "n/a"}, {"region": "MOCA", "area": "MOCA", "zone": "BO ROCHA SEC VELAZQUEZ"}, {"region": "ARECIBO", "area": "ARECIBO", "zone": "SEC JOBOS RIO ARRIBA"}, {"region": "ARECIBO", "area": "ARECIBO", "zone": "SECTOR VIA DEL TREN"}, {"region": "ISABELA", "area": "ISABELA", "zone": "URB. MANUEL CORCHADO"}, {"region": "AGUADILLA", "area": "AGUADILLA", "zone": "Bo. San Antonio"}, {"region": "AGUADILLA", "area": "AGUADILLA", "zone": "COND LADERAS DEL MAR"}, {"region": "GUAYNABO", "area": "GUAYNABO", "zone": "URB GARDEN HILLS"}, {"region": "CABO ROJO", "area": "CABO ROJO", "zone": "CABO ROJO P R"}, {"region": "CABO ROJO", "area": "CABO ROJO", "zone": "Casco Urbano Cabo Rojo"}, {"region": "CABO ROJO", "area": "CABO ROJO", "zone": "PARC CONDE AVILA CALLE PRINCIP"}, {"region": "BAYAMON", "area": "BAYAMON", "zone": "URB CAMPO ALEGRE"}, {"region": "AGUADA", "area": "AGUADA", "zone": "BO JAGUEY/ VILLA DE LA PAZ"}, {"region": "AGUADA", "area": "AGUADA", "zone": "Bo. Cerro Gordo"}, {"region": "TRUJILLO ALTO", "area": "TRUJILLO ALTO", "zone": "Bo. Carraizo"}, {"region": "TRUJILLO ALTO", "area": "TRUJILLO ALTO", "zone": "CUEVAS"}, {"region": "CAMUY", "area": "CAMUY", "zone": "BO PUERTOS ARRIBA"}, {"region": "JAYUYA", "area": "JAYUYA", "zone": "BO. VEGUITA ZAMAS"}, {"region": "JAYUYA", "area": "JAYUYA", "zone": "Bo. Veguita"}, {"region": "CAYEY", "area": "CAYEY", "zone": "BO VEGAS SECTOR LOPEZ"}, {"region": "MANATI", "area": "MANATI", "zone": "BO. MONTEBELLO"}, {"region": "UTUADO", "area": "UTUADO", "zone": "BO CAONILLAS"}, {"region": "UTUADO", "area": "UTUADO", "zone": "BO VIVI ABAJO SECT LAS CUEVAS"}, {"region": "NAGUABO", "area": "NAGUABO", "zone": "PENA POBRE-PARC VIEJAS   27046"}, {"region": "SAN JUAN", "area": "SAN JUAN", "zone": "SAGRADO CORAZON"}, {"region": "CAGUAS", "area": "CAGUAS", "zone": "BO CANANBON RT 256"}, {"region": "CAGUAS", "area": "CAGUAS", "zone": "BORINQUEN PARK EDIF A APT 204"}, {"region": "CAGUAS", "area": "CAGUAS", "zone": "Bo. San Antonio"}, {"region": "CAGUAS", "area": "CAGUAS", "zone": "CAGUAS"}, {"region": "CEIBA", "area": "CEIBA", "zone": "Bo. Daguao Arriba"}, {"region": "YAUCO", "area": "YAUCO", "zone": "BO PORTUGUEZ SECT SAN PATRICIO"}]