[{"region": "COROZAL", "area": "COROZAL", "zone": "BO MANA SECTOR QUEBRADA FRIA"}, {"region": "COROZAL", "area": "COROZAL", "zone": "BO PALMAREJO/SECTOR LOS LLANOS"}, {"region": "COROZAL", "area": "COROZAL", "zone": "Bo. Palmarito"}, {"region": "CIALES", "area": "CIALES", "zone": "BDA JAGUAS SEC LA PITAHAYA"}, {"region": "CIALES", "area": "CIALES", "zone": "BO CIALITOS SEC CIALITO CENTRO"}, {"region": "CIALES", "area": "CIALES", "zone": "BO. CIALITOS"}, {"region": "LAS MARIAS", "area": "LAS MARIAS", "zone": "Bo. Cerrote"}, {"region": "LAS MARIAS", "area": "LAS MARIAS", "zone": "RIO CA\u00d1AS"}, {"region": "LAS MARIAS", "area": "LAS MARIAS", "zone": "SECTOR TRABAL-CASEY ARRIBA"}, {"region": "PATILLAS", "area": "PATILLAS", "zone": "Bo. Bajos"}, {"region": "DORADO", "area": "DORADO", "zone": "Urb. Costa De Oro"}, {"region": "HATILLO", "area": "HATILLO", "zone": "Barrio Capaez"}, {"region": "GUAYANILLA", "area": "GUAYANILLA", "zone": "SIERRA BAJA"}, {"region": "AGUAS BUENAS", "area": "AGUAS BUENAS", "zone": "BO SONADORA/SECT RODEO"}, {"region": "AGUAS BUENAS", "area": "AGUAS BUENAS", "zone": "Bo. Juan Asencio"}, {"region": "HUMACAO", "area": "HUMACAO", "zone": "BO. CANDELERO"}, {"region": "HUMACAO", "area": "HUMACAO", "zone": "BUENA VISTA"}, {"region": "HUMACAO", "area": "HUMACAO", "zone": "Bo. Collores"}, {"region": "LOIZA", "area": "LOIZA", "zone": "Bo. Torrecilla Baja"}, {"region": "LOIZA", "area": "LOIZA", "zone": "Urb. Vistas Del Oceano"}, {"region": "RIO GRANDE", "area": "RIO GRANDE", "zone": "Ave. Carretera # 3"}, {"region": "RIO GRANDE", "area": "RIO GRANDE", "zone": "Bo. Guzman Abajo"}, {"region": "RIO GRANDE", "area": "RIO GRANDE", "zone": "Bo. Zarzal"}, {"region": "RIO GRANDE", "area": "RIO GRANDE", "zone": "Casco Urbano Rio Grand"}, {"region": "RIO GRANDE", "area": "RIO GRANDE", "zone": "Parc. Samuel Davila"}, {"region": "COMERIO", "area": "COMERIO", "zone": "BO DONA ELENA SEC ZAMORA"}, {"region": "COMERIO", "area": "COMERIO", "zone": "Bo. Naranjo"}, {"region": "AIBONITO", "area": "AIBONITO", "zone": "Bo. Cuyon"}, {"region": "AIBONITO", "area": "AIBONITO", "zone": "Bo. Los Llanos"}, {"region": "RINCON", "area": "RINCON", "zone": "BO ATALAYA BOX-6127"}, {"region": "RINCON", "area": "RINCON", "zone": "Bo. Puntas"}, {"region": "RINCON", "area": "RINCON", "zone": "CALVACHE"}, {"region": "ANASCO", "area": "ANASCO", "zone": "Barrio Caracol"}, {"region": "ANASCO", "area": "ANASCO", "zone": "Bo. Quebrada Larga"}, {"region": "CIDRA", "area": "CIDRA", "zone": "Bo. Ceiba"}, {"region": "MOCA", "area": "MOCA", "zone": "NARANJO"}, {"region": "MOCA", "area": "MOCA", "zone": "PUEBLO"}, {"region": "MOCA", "area": "MOCA", "zone": "ROCHA"}, {"region": "YABUCOA", "area": "YABUCOA", "zone": "URB VILLA DEL RECREO 29010"}, {"region": "JUANA DIAZ", "area": "JUANA DIAZ", "zone": "BO JACAGUAS - OLLA ONDA FINAL"}, {"region": "JUANA DIAZ", "area": "JUANA DIAZ", "zone": "Bo. Rio Canas Arriba"}, {"region": "JUANA DIAZ", "area": "JUANA DIAZ", "zone": "SABANA LLANA"}, {"region": "JUANA DIAZ", "area": "JUANA DIAZ", "zone": "URB LAS FLORES"}, {"region": "LARES", "area": "LARES", "zone": "BARTOLO"}, {"region": "OROCOVIS", "area": "OROCOVIS", "zone": "BO BAUTA ARRIBA"}, {"region": "OROCOVIS", "area": "OROCOVIS", "zone": "BO GATO"}, {"region": "OROCOVIS", "area": "OROCOVIS", "zone": "Bo. Bermejas"}, {"region": "OROCOVIS", "area": "OROCOVIS", "zone": "Bo. Damian Arriba"}, {"region": "ARECIBO", "area": "ARECIBO", "zone": "Bo. Islote"}, {"region": "ARECIBO", "area": "ARECIBO", "zone": "Reparto Marquez"}, {"region": "ARECIBO", "area": "ARECIBO", "zone": "SEC ANIMAS FACTOR 1"}, {"region": "TOA ALTA", "area": "TOA ALTA", "zone": "Casco Urbano Toa Alta"}, {"region": "LAJAS", "area": "LAJAS", "zone": "PLAYA ROSADA LA PARGUERA"}, {"region": "LAJAS", "area": "LAJAS", "zone": "Urb. Estancias Del Par"}, {"region": "SANTA ISABEL", "area": "SANTA ISABEL", "zone": "BO DESCALABRADO/SEC JARAGUAZAL"}, {"region": "SANTA ISABEL", "area": "SANTA ISABEL", "zone": "JAUCA 2"}, {"region": "SANTA ISABEL", "area": "SANTA ISABEL", "zone": "URB VALLE COSTERO"}, {"region": "ISABELA", "area": "ISABELA", "zone": "BO LLANADAS/PONCITO/LA CABALLA"}, {"region": "ISABELA", "area": "ISABELA", "zone": "Bo. Llanadas"}, {"region": "ISABELA", "area": "ISABELA", "zone": "URB MANUEL CORCHADO"}, {"region": "SALINAS", "area": "SALINAS", "zone": "BO COCO NUEVO"}, {"region": "SALINAS", "area": "SALINAS", "zone": "BO COCO NUEVO PROY HUCAR"}, {"region": "SALINAS", "area": "SALINAS", "zone": "Bo. Lapas"}, {"region": "SALINAS", "area": "SALINAS", "zone": "HACIENDAS D JUAN COL FORTUNA"}, {"region": "SALINAS", "area": "SALINAS", "zone": "Zona Urbana Salinas"}, {"region": "HORMIGUEROS", "area": "HORMIGUEROS", "zone": "Sector Jaguitas"}, {"region": "HORMIGUEROS", "area": "HORMIGUEROS", "zone": "n/a"}, {"region": "AGUADILLA", "area": "AGUADILLA", "zone": "BO CORRALES"}, {"region": "AGUADILLA", "area": "AGUADILLA", "zone": "BO GUERRERO /ENTRADA VAQUERIA"}, {"region": "AGUADILLA", "area": "AGUADILLA", "zone": "Bo. San Antonio"}, {"region": "GUAYNABO", "area": "GUAYNABO", "zone": "Bo. Buen Pastor"}, {"region": "GUAYNABO", "area": "GUAYNABO", "zone": "Bo. Camarones"}, {"region": "GUAYNABO", "area": "GUAYNABO", "zone": "Bo. Frailes"}, {"region": "GUAYNABO", "area": "GUAYNABO", "zone": "Bo. Santa Rosa"}, {"region": "GUAYNABO", "area": "GUAYNABO", "zone": "Casco Urbano Guaynabo"}, {"region": "GUAYNABO", "area": "GUAYNABO", "zone": "Cond. Valles de Torrimar"}, {"region": "GUAYNABO", "area": "GUAYNABO", "zone": "Condominio Gemini"}, {"region": "GUAYNABO", "area": "GUAYNABO", "zone": "Condominios Ciudadela"}, {"region": "GUAYNABO", "area": "GUAYNABO", "zone": "MAMEY"}, {"region": "GUAYNABO", "area": "GUAYNABO", "zone": "SONADORA ALTA SEC MACHUCA"}, {"region": "GUAYNABO", "area": "GUAYNABO", "zone": "Urb. Alturas de Santa Maria"}, {"region": "GUAYNABO", "area": "GUAYNABO", "zone": "Urb. Apolo"}, {"region": "GUAYNABO", "area": "GUAYNABO", "zone": "Urb. Colimar"}, {"region": "GUAYNABO", "area": "GUAYNABO", "zone": "Urb. Los Frailes"}, {"region": "GUAYNABO", "area": "GUAYNABO", "zone": "Urb. Los Manantiales"}, {"region": "PENUELAS", "area": "PENUELAS", "zone": "BO CEBORUCO"}, {"region": "PENUELAS", "area": "PENUELAS", "zone": "n/a"}, {"region": "CAROLINA", "area": "CAROLINA", "zone": "BO. CARRUZOS"}, {"region": "CAROLINA", "area": "CAROLINA", "zone": "SABANA ABAJO"}, {"region": "CAROLINA", "area": "CAROLINA", "zone": "URB COUNTRY CLUB"}, {"region": "BARRANQUITAS", "area": "BARRANQUITAS", "zone": "Bo. Palmarito"}, {"region": "BARRANQUITAS", "area": "BARRANQUITAS", "zone": "Bo. Palo Hincado"}, {"region": "BARRANQUITAS", "area": "BARRANQUITAS", "zone": "Bo. Quebradillas"}, {"region": "BARRANQUITAS", "area": "BARRANQUITAS", "zone": "QUEBRADA GRANDE"}, {"region": "ADJUNTAS", "area": "ADJUNTAS", "zone": "ADJUNTAS"}, {"region": "ADJUNTAS", "area": "ADJUNTAS", "zone": "BO CASTANER"}, {"region": "ADJUNTAS", "area": "ADJUNTAS", "zone": "Bo. Limani"}, {"region": "ADJUNTAS", "area": "ADJUNTAS", "zone": "Bo. Portillo Arriba"}, {"region": "ADJUNTAS", "area": "ADJUNTAS", "zone": "Casco Urbano Adjuntas"}, {"region": "SAN GERMAN", "area": "SAN GERMAN", "zone": "Bo. Cain Alto"}, {"region": "SAN GERMAN", "area": "SAN GERMAN", "zone": "Bo. Guama"}, {"region": "SAN GERMAN", "area": "SAN GERMAN", "zone": "COTUI INTER. 394"}, {"region": "SAN GERMAN", "area": "SAN GERMAN", "zone": "MINILLAS SAN GERMAN"}, {"region": "SAN GERMAN", "area": "SAN GERMAN", "zone": "PARC CAROLINA/BO DUEY BAJO"}, {"region": "SAN GERMAN", "area": "SAN GERMAN", "zone": "Sector Minillas Alto"}, {"region": "SAN GERMAN", "area": "SAN GERMAN", "zone": "Sector Minillas Valle"}, {"region": "SAN GERMAN", "area": "SAN GERMAN", "zone": "Urb. Villa Interameric"}, {"region": "TOA BAJA", "area": "TOA BAJA", "zone": "Bo. Pajaros"}, {"region": "TOA BAJA", "area": "TOA BAJA", "zone": "CAGUABO/ENT DESP EL CHOCHE"}, {"region": "BAYAMON", "area": "BAYAMON", "zone": "BO CERRO GORDO"}, {"region": "BAYAMON", "area": "BAYAMON", "zone": "Bo. Cerro Gordo"}, {"region": "BAYAMON", "area": "BAYAMON", "zone": "Bo. Dajaos"}, {"region": "BAYAMON", "area": "BAYAMON", "zone": "Bo. Guaraguao Arriba"}, {"region": "BAYAMON", "area": "BAYAMON", "zone": "MINILLAS"}, {"region": "BAYAMON", "area": "BAYAMON", "zone": "URB REXVILLE"}, {"region": "BAYAMON", "area": "BAYAMON", "zone": "Urb. Forest Hills"}, {"region": "BAYAMON", "area": "BAYAMON", "zone": "Urb. Jard. De Casablanca"}, {"region": "BAYAMON", "area": "BAYAMON", "zone": "Urb. Lomas Verdes"}, {"region": "BAYAMON", "area": "BAYAMON", "zone": "Urb. Santa Juanita"}, {"region": "BAYAMON", "area": "BAYAMON", "zone": "Urb. Sierra Linda"}, {"region": "CANOVANAS", "area": "CANOVANAS", "zone": "Bo. Campo Rico"}, {"region": "CANOVANAS", "area": "CANOVANAS", "zone": "CANOVANAS"}, {"region": "CANOVANAS", "area": "CANOVANAS", "zone": "HATO PUERCO"}, {"region": "CANOVANAS", "area": "CANOVANAS", "zone": "URB JARDINES DE CANOVANAS"}, {"region": "AGUADA", "area": "AGUADA", "zone": "BO GUANIQUILLA"}, {"region": "AGUADA", "area": "AGUADA", "zone": "BO QUEBRADA LARGA"}, {"region": "VILLALBA", "area": "VILLALBA", "zone": "Bo. Caonillas Arriba"}, {"region": "VILLALBA", "area": "VILLALBA", "zone": "Bo. Jagueyes"}, {"region": "VILLALBA", "area": "VILLALBA", "zone": "HATO PUERCO ARRIBA"}, {"region": "VILLALBA", "area": "VILLALBA", "zone": "Sector El Pino"}, {"region": "GURABO", "area": "GURABO", "zone": "Bo. Navarro"}, {"region": "MARICAO", "area": "MARICAO", "zone": "Sector Los Cuadros"}, {"region": "TRUJILLO ALTO", "area": "TRUJILLO ALTO", "zone": "BO LA GLORIA"}, {"region": "TRUJILLO ALTO", "area": "TRUJILLO ALTO", "zone": "Bo. Saint Just"}, {"region": "TRUJILLO ALTO", "area": "TRUJILLO ALTO", "zone": "ST. JUST"}, {"region": "CAMUY", "area": "CAMUY", "zone": "BO PIEDRA GORDA"}, {"region": "CAMUY", "area": "CAMUY", "zone": "Bo. Membrillo"}, {"region": "CAMUY", "area": "CAMUY", "zone": "Bo. Yeguada"}, {"region": "PONCE", "area": "PONCE", "zone": "BARRIO MARAGUEZ"}, {"region": "PONCE", "area": "PONCE", "zone": "BO MONTES LLANOS"}, {"region": "PONCE", "area": "PONCE", "zone": "BO QDA LIMON SITIO RINCON"}, {"region": "PONCE", "area": "PONCE", "zone": "BO REAL ANON/AGUSTINILLO CQ-00"}, {"region": "PONCE", "area": "PONCE", "zone": "BO SAN PATRICIO/LA MOCHA INT"}, {"region": "PONCE", "area": "PONCE", "zone": "CANAS"}, {"region": "PONCE", "area": "PONCE", "zone": "COTO LAUREL"}, {"region": "PONCE", "area": "PONCE", "zone": "Casco Urbano Ponce"}, {"region": "PONCE", "area": "PONCE", "zone": "EL TUQUE"}, {"region": "PONCE", "area": "PONCE", "zone": "EXT LA RAMBLA"}, {"region": "PONCE", "area": "PONCE", "zone": "EXT URB SANTA TERESITA"}, {"region": "PONCE", "area": "PONCE", "zone": "PARC MARUENO"}, {"region": "PONCE", "area": "PONCE", "zone": "PLAZOLETA LAS AMERICAS"}, {"region": "PONCE", "area": "PONCE", "zone": "Res. Lirios Del Sur"}, {"region": "PONCE", "area": "PONCE", "zone": "URB BARAMAYA"}, {"region": "PONCE", "area": "PONCE", "zone": "URB FLAMBOYANES"}, {"region": "PONCE", "area": "PONCE", "zone": "URB JARDINES FAGOT"}, {"region": "PONCE", "area": "PONCE", "zone": "Zona Urbana Ponce"}, {"region": "JAYUYA", "area": "JAYUYA", "zone": "COM MAMEYES SEC LIMON DE MARQU"}, {"region": "JAYUYA", "area": "JAYUYA", "zone": "MAMEYES ARRIBA"}, {"region": "CAYEY", "area": "CAYEY", "zone": "MONTE LLANO"}, {"region": "CAYEY", "area": "CAYEY", "zone": "URB ALTURAS DE BEATRIZ"}, {"region": "MANATI", "area": "MANATI", "zone": "BO.COTO SUR-EBP TANQUE MILLON"}, {"region": "MANATI", "area": "MANATI", "zone": "Bo. Bajura Afuera"}, {"region": "COAMO", "area": "COAMO", "zone": "Carr. PR 14"}, {"region": "COAMO", "area": "COAMO", "zone": "Carr. PR 545"}, {"region": "COAMO", "area": "COAMO", "zone": "SALIDA PARA SANTA CATALINA"}, {"region": "COAMO", "area": "COAMO", "zone": "SECTOR COTO RUIZ BO LOS LLANOS"}, {"region": "UTUADO", "area": "UTUADO", "zone": "Bo. Rio Abajo"}, {"region": "UTUADO", "area": "UTUADO", "zone": "TETUAN"}, {"region": "NAGUABO", "area": "NAGUABO", "zone": "PENA POBRE EL PINON 27022"}, {"region": "SAN JUAN", "area": "SAN JUAN", "zone": "Ave. 65 De Infanteria"}, {"region": "SAN JUAN", "area": "SAN JUAN", "zone": "Ave. Roosevelt"}, {"region": "SAN JUAN", "area": "SAN JUAN", "zone": "Bda. Bitumul HR"}, {"region": "SAN JUAN", "area": "SAN JUAN", "zone": "Bo. Cupey Alto"}, {"region": "SAN JUAN", "area": "SAN JUAN", "zone": "Bo. Cupey Bajo"}, {"region": "SAN JUAN", "area": "SAN JUAN", "zone": "Bo. Obrero"}, {"region": "SAN JUAN", "area": "SAN JUAN", "zone": "Bo. Villa Palmeras Sa"}, {"region": "SAN JUAN", "area": "SAN JUAN", "zone": "CAIMITO"}, {"region": "SAN JUAN", "area": "SAN JUAN", "zone": "COND ALTURAS DE CALDAS"}, {"region": "SAN JUAN", "area": "SAN JUAN", "zone": "CUPEY"}, {"region": "SAN JUAN", "area": "SAN JUAN", "zone": "Cond. villas del Senorial"}, {"region": "SAN JUAN", "area": "SAN JUAN", "zone": "Isla Grande"}, {"region": "SAN JUAN", "area": "SAN JUAN", "zone": "MONACILLO URBANO"}, {"region": "SAN JUAN", "area": "SAN JUAN", "zone": "PORTAL DE SANTA MARIA"}, {"region": "SAN JUAN", "area": "SAN JUAN", "zone": "Sector Ocean Park"}, {"region": "SAN JUAN", "area": "SAN JUAN", "zone": "Urb. Altamesa"}, {"region": "SAN JUAN", "area": "SAN JUAN", "zone": "Urb. Caldas"}, {"region": "SAN JUAN", "area": "SAN JUAN", "zone": "Urb. La Cumbre"}, {"region": "SAN JUAN", "area": "SAN JUAN", "zone": "Urb. Monte Verde Real"}, {"region": "SAN JUAN", "area": "SAN JUAN", "zone": "Urb. Purple Tree"}, {"region": "SAN JUAN", "area": "SAN JUAN", "zone": "Urb. Reparto Metro SE"}, {"region": "SAN JUAN", "area": "SAN JUAN", "zone": "Urb. Roosevelt"}, {"region": "SAN JUAN", "area": "SAN JUAN", "zone": "Urb. San Francisco"}, {"region": "SAN JUAN", "area": "SAN JUAN", "zone": "Urb. San Ignacio"}, {"region": "SAN JUAN", "area": "SAN JUAN", "zone": "Zona Industrial Julia"}, {"region": "SAN JUAN", "area": "SAN JUAN", "zone": "n/a"}, {"region": "GUANICA", "area": "GUANICA", "zone": "Bo. Magueyes"}, {"region": "CAGUAS", "area": "CAGUAS", "zone": "BAIROA"}, {"region": "CAGUAS", "area": "CAGUAS", "zone": "Bo. San Antonio"}, {"region": "CAGUAS", "area": "CAGUAS", "zone": "REGIONAL CAGUAS"}, {"region": "CAGUAS", "area": "CAGUAS", "zone": "TOMAS DE CASTRO CAGUAS"}, {"region": "MOROVIS", "area": "MOROVIS", "zone": "BO MOROVIS SUR / MOROVIS PLAZA"}, {"region": "MOROVIS", "area": "MOROVIS", "zone": "PERCHAS SECT LOS NARANJOS"}, {"region": "NARANJITO", "area": "NARANJITO", "zone": "BO ANONES-EL PALMAR"}, {"region": "NARANJITO", "area": "NARANJITO", "zone": "BO LOMAS VALLES"}, {"region": "NARANJITO", "area": "NARANJITO", "zone": "BO NUEVO  BUNKER HILL"}, {"region": "NARANJITO", "area": "NARANJITO", "zone": "BO.ANONES/SECT.EL MIRADOR"}, {"region": "NARANJITO", "area": "NARANJITO", "zone": "Bo. Anones"}, {"region": "NARANJITO", "area": "NARANJITO", "zone": "Bo. Cedro Arriba"}, {"region": "NARANJITO", "area": "NARANJITO", "zone": "Bo. Guadiana"}, {"region": "VEGA BAJA", "area": "VEGA BAJA", "zone": "Bo. Algarrobo"}, {"region": "VEGA BAJA", "area": "VEGA BAJA", "zone": "LAS GRANJAS"}, {"region": "VEGA BAJA", "area": "VEGA BAJA", "zone": "PARCELAS AMADEO"}, {"region": "VEGA BAJA", "area": "VEGA BAJA", "zone": "Playa Vega Baja"}, {"region": "VEGA BAJA", "area": "VEGA BAJA", "zone": "VILLA COLOMBO"}, {"region": "MAYAGUEZ", "area": "MAYAGUEZ", "zone": "Bo. Leguisano"}, {"region": "MAYAGUEZ", "area": "MAYAGUEZ", "zone": "Urb. Flamboyan"}, {"region": "YAUCO", "area": "YAUCO", "zone": "BO NARANJO EL VERDE ABAJO"}, {"region": "YAUCO", "area": "YAUCO", "zone": "BO RIO PRIETO SEC CARRIZALES"}, {"region": "YAUCO", "area": "YAUCO", "zone": "Bo. Rancheras"}]