[{"region": "DORADO", "area": "DORADO", "zone": "MAGUAYO"}, {"region": "DORADO", "area": "DORADO", "zone": "URB NUEVA COMUNIDAD ARENAS"}, {"region": "BARCELONETA", "area": "BARCELONETA", "zone": "BO GARROCHALES-SECTOR MENDEZ"}, {"region": "BARCELONETA", "area": "BARCELONETA", "zone": "GARROCHALES - SECTOR LA CITE"}, {"region": "AGUAS BUENAS", "area": "AGUAS BUENAS", "zone": "BO BAYAMONCITO SECTOR EL PUNTO"}, {"region": "AGUAS BUENAS", "area": "AGUAS BUENAS", "zone": "BO JAGUEYES"}, {"region": "HUMACAO", "area": "HUMACAO", "zone": "MABU"}, {"region": "COMERIO", "area": "COMERIO", "zone": "BO CEJAS"}, {"region": "CIDRA", "area": "CIDRA", "zone": "URB ESTANCIAS DE CIDRA"}, {"region": "OROCOVIS", "area": "OROCOVIS", "zone": "BO GATO PERCHAS, SEC NARANJO"}, {"region": "OROCOVIS", "area": "OROCOVIS", "zone": "MATA DE CA{A OROCOVIS"}, {"region": "ARECIBO", "area": "ARECIBO", "zone": "RES VISTA AZUL"}, {"region": "ARECIBO", "area": "ARECIBO", "zone": "SABANA HOYOS/ARROZAL LOS MUERT"}, {"region": "TOA ALTA", "area": "TOA ALTA", "zone": "Bo. Contorno"}, {"region": "SABANA GRANDE", "area": "SABANA GRANDE", "zone": "PARCELAS MAGINAS"}, {"region": "SAN SEBASTIAN", "area": "SAN SEBASTIAN", "zone": "BO HOYAMALA/SALAS VARELA"}, {"region": "AGUADILLA", "area": "AGUADILLA", "zone": "BO PALMAR"}, {"region": "GUAYNABO", "area": "GUAYNABO", "zone": "BO MAMEY 1"}, {"region": "GUAYNABO", "area": "GUAYNABO", "zone": "HATO NUEVO"}, {"region": "CABO ROJO", "area": "CABO ROJO", "zone": "SECTOR COMBATE"}, {"region": "PENUELAS", "area": "PENUELAS", "zone": "BO JAGUAS SECTOR MARTILLO"}, {"region": "ADJUNTAS", "area": "ADJUNTAS", "zone": "Bo. Juan Gonzalez #2"}, {"region": "TOA BAJA", "area": "TOA BAJA", "zone": "BO PAJAROS TOA BAJA 00759"}, {"region": "TOA BAJA", "area": "TOA BAJA", "zone": "Bo. Candelaria Arenas"}, {"region": "TOA BAJA", "area": "TOA BAJA", "zone": "LEVITTOWN LAKES"}, {"region": "TOA BAJA", "area": "TOA BAJA", "zone": "VILLA HOSTOS CAMPANILLAS"}, {"region": "BAYAMON", "area": "BAYAMON", "zone": "URB LOMAS VERDES"}, {"region": "CANOVANAS", "area": "CANOVANAS", "zone": "Bo. Quebrada Prieta"}, {"region": "VILLALBA", "area": "VILLALBA", "zone": "Casco Urbano Villalba"}, {"region": "LAS PIEDRAS", "area": "LAS PIEDRAS", "zone": "TEJAS"}, {"region": "TRUJILLO ALTO", "area": "TRUJILLO ALTO", "zone": "BO QDA GRANDE"}, {"region": "PONCE", "area": "PONCE", "zone": "BO PASTILLO ALTO"}, {"region": "PONCE", "area": "PONCE", "zone": "CANAS"}, {"region": "CAYEY", "area": "CAYEY", "zone": "BO QUEBRADA ARRIBA"}, {"region": "CAYEY", "area": "CAYEY", "zone": "BO RINCON MORRILLO"}, {"region": "MANATI", "area": "MANATI", "zone": "BUZON 4 BO PALO ALTO"}, {"region": "COAMO", "area": "COAMO", "zone": "BO LLANOS"}, {"region": "SAN JUAN", "area": "SAN JUAN", "zone": "COND DE LA FUENTE"}, {"region": "SAN JUAN", "area": "SAN JUAN", "zone": "CUPEY"}, {"region": "SAN JUAN", "area": "SAN JUAN", "zone": "SAN JUAN PR 00907-0000"}, {"region": "SAN JUAN", "area": "SAN JUAN", "zone": "URB BALDRICH"}, {"region": "SAN JUAN", "area": "SAN JUAN", "zone": "URB CAPARRA TERRACE"}, {"region": "SAN JUAN", "area": "SAN JUAN", "zone": "URB EL COMANDANTE"}, {"region": "SAN JUAN", "area": "SAN JUAN", "zone": "URB FAIR VIEW"}, {"region": "SAN JUAN", "area": "SAN JUAN", "zone": "URB LA RIVIERA"}, {"region": "SAN JUAN", "area": "SAN JUAN", "zone": "Urb. Puerto Nuevo Calles NE"}, {"region": "SAN JUAN", "area": "SAN JUAN", "zone": "Zona Ind. Tres Monjita"}, {"region": "NARANJITO", "area": "NARANJITO", "zone": "BO CEDRO ARRIBA"}, {"region": "NARANJITO", "area": "NARANJITO", "zone": "BO LOMAS JAGUAS LOS BERRIOS"}, {"region": "NARANJITO", "area": "NARANJITO", "zone": "BO. GUADIANASECTOR HNDEZ."}, {"region": "NARANJITO", "area": "NARANJITO", "zone": "Bo. Cedro Abajo"}, {"region": "VEGA BAJA", "area": "VEGA BAJA", "zone": "Bo. Pugnado Adentro"}, {"region": "SAN LORENZO", "area": "SAN LORENZO", "zone": "BO HATO   CERRO LOS PAGAN"}, {"region": "SAN LORENZO", "area": "SAN LORENZO", "zone": "BO QUEMADOS/SECT MONCHO CAY"}, {"region": "FAJARDO", "area": "FAJARDO", "zone": "FAJARDO"}, {"region": "MAYAGUEZ", "area": "MAYAGUEZ", "zone": "Urb. Mayag\u00fcez Terrace"}, {"region": "YAUCO", "area": "YAUCO", "zone": "BO QUEBRADAS/SECT JAVILLA"}, {"region": "YAUCO", "area": "YAUCO", "zone": "Bo. Frailes"}]