[{"region": "CIALES", "area": "CIALES", "zone": "BO CIALITOS CENTRO"}, {"region": "CIALES", "area": "CIALES", "zone": "BO POZAS"}, {"region": "LAS MARIAS", "area": "LAS MARIAS", "zone": "Bo. Cerrote"}, {"region": "PATILLAS", "area": "PATILLAS", "zone": "BO MARIN ALTOSECT LOS HUERTAS"}, {"region": "PATILLAS", "area": "PATILLAS", "zone": "Bo. Margote"}, {"region": "DORADO", "area": "DORADO", "zone": "MAGUAYO"}, {"region": "GUAYAMA", "area": "GUAYAMA", "zone": "Bo. Pozuelo (Entrada)"}, {"region": "GUAYAMA", "area": "GUAYAMA", "zone": "PALMAS ALTAS CANCHA BALONCESTO"}, {"region": "GUAYAMA", "area": "GUAYAMA", "zone": "URB HACIENDA LOS RECREOS"}, {"region": "AGUAS BUENAS", "area": "AGUAS BUENAS", "zone": "BAIROA"}, {"region": "AGUAS BUENAS", "area": "AGUAS BUENAS", "zone": "BO SONADORA/SECT RODEO"}, {"region": "AGUAS BUENAS", "area": "AGUAS BUENAS", "zone": "JAGUEYES"}, {"region": "AGUAS BUENAS", "area": "AGUAS BUENAS", "zone": "Res. Vista Alegre"}, {"region": "AGUAS BUENAS", "area": "AGUAS BUENAS", "zone": "SECTOR LA PAJILLA/BO HATO NUEV"}, {"region": "AGUAS BUENAS", "area": "AGUAS BUENAS", "zone": "SONADORA/LA MARQUESA"}, {"region": "HUMACAO", "area": "HUMACAO", "zone": "Bo. Candelero Abajo"}, {"region": "HUMACAO", "area": "HUMACAO", "zone": "CATANO                   26007"}, {"region": "HUMACAO", "area": "HUMACAO", "zone": "MARIANA II"}, {"region": "LOIZA", "area": "LOIZA", "zone": "BO MINI MINI LOIZA ALDEA"}, {"region": "LOIZA", "area": "LOIZA", "zone": "Parc. Villa Santos"}, {"region": "RIO GRANDE", "area": "RIO GRANDE", "zone": "SEC LAS YAYAS BO LOMAS"}, {"region": "COMERIO", "area": "COMERIO", "zone": "Bo. Pinas"}, {"region": "COMERIO", "area": "COMERIO", "zone": "VEGA REDONDA LA MORA-POLLERAS"}, {"region": "VEGA ALTA", "area": "VEGA ALTA", "zone": "BO SABANA HOYOS"}, {"region": "AIBONITO", "area": "AIBONITO", "zone": "CAONILLAS"}, {"region": "AIBONITO", "area": "AIBONITO", "zone": "PLATA"}, {"region": "AIBONITO", "area": "AIBONITO", "zone": "Urb. Jatibonito"}, {"region": "RINCON", "area": "RINCON", "zone": "BO RIO GRANDESEC PEDRO ROSADO"}, {"region": "MOCA", "area": "MOCA", "zone": "Bo. Cerro Gordo"}, {"region": "MOCA", "area": "MOCA", "zone": "Bo. Cuchillas"}, {"region": "MOCA", "area": "MOCA", "zone": "Bo. La Cruz"}, {"region": "JUANA DIAZ", "area": "JUANA DIAZ", "zone": "URB HERMANOS SANTIAGO"}, {"region": "JUANA DIAZ", "area": "JUANA DIAZ", "zone": "URB VILLA DEL SOL"}, {"region": "LARES", "area": "LARES", "zone": "BO ESPINO CEIBA"}, {"region": "LARES", "area": "LARES", "zone": "BUENOS AIRES SECT LA AMERICA"}, {"region": "LARES", "area": "LARES", "zone": "ESPINO CEIBA"}, {"region": "LARES", "area": "LARES", "zone": "MIRASOL"}, {"region": "LARES", "area": "LARES", "zone": "MIRASOL SECT CALCERRADA"}, {"region": "LARES", "area": "LARES", "zone": "Sector Castaner"}, {"region": "OROCOVIS", "area": "OROCOVIS", "zone": "BO BARROS SECC LIMONES"}, {"region": "OROCOVIS", "area": "OROCOVIS", "zone": "BO BAUTA ABAJO LA FRANCIA"}, {"region": "OROCOVIS", "area": "OROCOVIS", "zone": "BO BAUTA ABAJO SEC SECTOR TAIT"}, {"region": "OROCOVIS", "area": "OROCOVIS", "zone": "Bo. Bermejas"}, {"region": "OROCOVIS", "area": "OROCOVIS", "zone": "Bo. Damian Abajo"}, {"region": "ARECIBO", "area": "ARECIBO", "zone": "HATO VIEJO"}, {"region": "ARECIBO", "area": "ARECIBO", "zone": "RIO ARRIBA"}, {"region": "TOA ALTA", "area": "TOA ALTA", "zone": "Bo. Quebrada Arenas"}, {"region": "TOA ALTA", "area": "TOA ALTA", "zone": "ORTIZ"}, {"region": "TOA ALTA", "area": "TOA ALTA", "zone": "QUEBRADA ARENAS"}, {"region": "SABANA GRANDE", "area": "SABANA GRANDE", "zone": "Bo. Susua"}, {"region": "SANTA ISABEL", "area": "SANTA ISABEL", "zone": "BO DESCALABRADO CARR 545 KM 1."}, {"region": "ISABELA", "area": "ISABELA", "zone": "BAJOS(ERNESTO MERCADO ALVAREZ)"}, {"region": "ISABELA", "area": "ISABELA", "zone": "BEJUCOS"}, {"region": "ISABELA", "area": "ISABELA", "zone": "BO. PLANAS 2 CUESTA EL PITIRRE"}, {"region": "SALINAS", "area": "SALINAS", "zone": "BO COCO NUEVO"}, {"region": "SALINAS", "area": "SALINAS", "zone": "BO. COCO NUEVO"}, {"region": "AGUADILLA", "area": "AGUADILLA", "zone": "BO CAMASEYES CJN FELICIANO"}, {"region": "AGUADILLA", "area": "AGUADILLA", "zone": "Bo. Aguacate"}, {"region": "AGUADILLA", "area": "AGUADILLA", "zone": "Bo. Camaseyes"}, {"region": "CULEBRA", "area": "CULEBRA", "zone": "FRAILE"}, {"region": "GUAYNABO", "area": "GUAYNABO", "zone": "Bo. Camarones"}, {"region": "GUAYNABO", "area": "GUAYNABO", "zone": "URB GOLDEN GATE"}, {"region": "GUAYNABO", "area": "GUAYNABO", "zone": "URB MUNOZ RIVERA"}, {"region": "GUAYNABO", "area": "GUAYNABO", "zone": "URB VILLA CAPARRA"}, {"region": "JUNCOS", "area": "JUNCOS", "zone": "CEIBA SUR"}, {"region": "CABO ROJO", "area": "CABO ROJO", "zone": "BO BOQUERON SEC EL CANO"}, {"region": "CABO ROJO", "area": "CABO ROJO", "zone": "BOQUERON / SECTOR EL COROZO"}, {"region": "CABO ROJO", "area": "CABO ROJO", "zone": "CAMINO MARCIAL RIVERA"}, {"region": "CABO ROJO", "area": "CABO ROJO", "zone": "Casco Urbano Cabo Rojo"}, {"region": "PENUELAS", "area": "PENUELAS", "zone": "BO TALLABOA ALTA IIISEROTE"}, {"region": "PENUELAS", "area": "PENUELAS", "zone": "TALLABOA ALTA III LA MOCA"}, {"region": "CAROLINA", "area": "CAROLINA", "zone": "BO CANOVANILLAS"}, {"region": "CAROLINA", "area": "CAROLINA", "zone": "CACAO"}, {"region": "CAROLINA", "area": "CAROLINA", "zone": "CEDRO"}, {"region": "CAROLINA", "area": "CAROLINA", "zone": "URB COUNTRY CLUB"}, {"region": "CAROLINA", "area": "CAROLINA", "zone": "URB VILLA CAROLINA"}, {"region": "CAROLINA", "area": "CAROLINA", "zone": "Urb. Villa Carolina I"}, {"region": "CAROLINA", "area": "CAROLINA", "zone": "VILLA CAROLINA"}, {"region": "BARRANQUITAS", "area": "BARRANQUITAS", "zone": "BO PALO HINCADO SEC PINONAS"}, {"region": "ADJUNTAS", "area": "ADJUNTAS", "zone": "BO VEGAS ABAJO"}, {"region": "SAN GERMAN", "area": "SAN GERMAN", "zone": "Sector Ancones"}, {"region": "TOA BAJA", "area": "TOA BAJA", "zone": "MEDIA LUNA"}, {"region": "TOA BAJA", "area": "TOA BAJA", "zone": "SABANA SECA"}, {"region": "BAYAMON", "area": "BAYAMON", "zone": "BO NUEVO / SECT LOPEZ"}, {"region": "BAYAMON", "area": "BAYAMON", "zone": "Bo. Santa Olaya"}, {"region": "BAYAMON", "area": "BAYAMON", "zone": "HATO TEJAS"}, {"region": "BAYAMON", "area": "BAYAMON", "zone": "MINILLAS"}, {"region": "BAYAMON", "area": "BAYAMON", "zone": "NUEVO"}, {"region": "BAYAMON", "area": "BAYAMON", "zone": "URB ALTURAS DE FLAMBOYAN"}, {"region": "BAYAMON", "area": "BAYAMON", "zone": "URB MANSIONES SIERRA TAINA"}, {"region": "BAYAMON", "area": "BAYAMON", "zone": "Urb. Magnolia Gardens"}, {"region": "CANOVANAS", "area": "CANOVANAS", "zone": "Bo. Campo Rico"}, {"region": "CANOVANAS", "area": "CANOVANAS", "zone": "Bo. Palma Sola"}, {"region": "CANOVANAS", "area": "CANOVANAS", "zone": "HATO PUERCO"}, {"region": "CANOVANAS", "area": "CANOVANAS", "zone": "LOIZA VALLEY CANOVANAS"}, {"region": "CANOVANAS", "area": "CANOVANAS", "zone": "PARK VIEW TERRACE"}, {"region": "CANOVANAS", "area": "CANOVANAS", "zone": "SECT. CANOVANILLAS"}, {"region": "CANOVANAS", "area": "CANOVANAS", "zone": "Urb. Loiza Valley"}, {"region": "AGUADA", "area": "AGUADA", "zone": "BO MAMEY"}, {"region": "VILLALBA", "area": "VILLALBA", "zone": "BO BO CAONILLAS ABAJO"}, {"region": "VILLALBA", "area": "VILLALBA", "zone": "BO CAMARONES"}, {"region": "VILLALBA", "area": "VILLALBA", "zone": "BO CAONILLAS ABAJO"}, {"region": "VILLALBA", "area": "VILLALBA", "zone": "BO CAONILLAS ARRIBA -SIERRITA"}, {"region": "VILLALBA", "area": "VILLALBA", "zone": "BO HATILLO/PARC TOA VACA"}, {"region": "VILLALBA", "area": "VILLALBA", "zone": "BO HIGUERO"}, {"region": "VILLALBA", "area": "VILLALBA", "zone": "BO HIGUERO/LOS TORRES"}, {"region": "VILLALBA", "area": "VILLALBA", "zone": "HATO PUERCO ARRIBA"}, {"region": "GURABO", "area": "GURABO", "zone": "BO. NAVARRO"}, {"region": "GURABO", "area": "GURABO", "zone": "BO.NAVARRO/SECT LA PACHANGA"}, {"region": "GURABO", "area": "GURABO", "zone": "Bo. Celada Carrete"}, {"region": "GURABO", "area": "GURABO", "zone": "HATO NUEVO"}, {"region": "GURABO", "area": "GURABO", "zone": "RINCON"}, {"region": "MARICAO", "area": "MARICAO", "zone": "BO INDIERA BAJA"}, {"region": "MARICAO", "area": "MARICAO", "zone": "MARICAO AFUERA"}, {"region": "LAS PIEDRAS", "area": "LAS PIEDRAS", "zone": "Bo. Quebrada Grande"}, {"region": "LAS PIEDRAS", "area": "LAS PIEDRAS", "zone": "Bo. Tejas"}, {"region": "LAS PIEDRAS", "area": "LAS PIEDRAS", "zone": "QUEBRADA GRANDE          R-012"}, {"region": "TRUJILLO ALTO", "area": "TRUJILLO ALTO", "zone": "BO CARRAIZO ABAJO"}, {"region": "TRUJILLO ALTO", "area": "TRUJILLO ALTO", "zone": "BO LOS BARROS CAM LOS MORALES"}, {"region": "TRUJILLO ALTO", "area": "TRUJILLO ALTO", "zone": "BO SAINT JUST"}, {"region": "TRUJILLO ALTO", "area": "TRUJILLO ALTO", "zone": "Bo. Quebrada Grande"}, {"region": "TRUJILLO ALTO", "area": "TRUJILLO ALTO", "zone": "COLINAS DE FAIR VIEW"}, {"region": "TRUJILLO ALTO", "area": "TRUJILLO ALTO", "zone": "HACIENDAS DEL LAGO"}, {"region": "TRUJILLO ALTO", "area": "TRUJILLO ALTO", "zone": "PARC 41 BASE 1A BO BETANIA"}, {"region": "TRUJILLO ALTO", "area": "TRUJILLO ALTO", "zone": "SAINT JUST"}, {"region": "TRUJILLO ALTO", "area": "TRUJILLO ALTO", "zone": "SECT MATIENZO BO TRUJILLO"}, {"region": "TRUJILLO ALTO", "area": "TRUJILLO ALTO", "zone": "URB ENCANTADA /LA ANTIGUA"}, {"region": "PONCE", "area": "PONCE", "zone": "BDA BELGICA"}, {"region": "PONCE", "area": "PONCE", "zone": "BO BUYONES"}, {"region": "PONCE", "area": "PONCE", "zone": "BO REAL ANON"}, {"region": "PONCE", "area": "PONCE", "zone": "BO RUCIO SECT BELLEZA"}, {"region": "PONCE", "area": "PONCE", "zone": "Bda. Borinquen"}, {"region": "PONCE", "area": "PONCE", "zone": "COM CANAS / EL TUQUE"}, {"region": "PONCE", "area": "PONCE", "zone": "CUARTO"}, {"region": "PONCE", "area": "PONCE", "zone": "PLAYA"}, {"region": "PONCE", "area": "PONCE", "zone": "RES LA GUADALUPE"}, {"region": "PONCE", "area": "PONCE", "zone": "SEXTO"}, {"region": "PONCE", "area": "PONCE", "zone": "URB EL BOSQUE"}, {"region": "PONCE", "area": "PONCE", "zone": "URB HILLCREST VILLAGE"}, {"region": "PONCE", "area": "PONCE", "zone": "URB JARDINES DE PONCE"}, {"region": "JAYUYA", "area": "JAYUYA", "zone": "BO COABEY"}, {"region": "COAMO", "area": "COAMO", "zone": "BO LOS LLANOS/PARCELAS NUEVAS"}, {"region": "COAMO", "area": "COAMO", "zone": "SAN ILDEFONSO SABANA HOYOS"}, {"region": "UTUADO", "area": "UTUADO", "zone": "Bo. Tetuan III"}, {"region": "NAGUABO", "area": "NAGUABO", "zone": "URB RAMON RIVERO RL 27015"}, {"region": "SAN JUAN", "area": "SAN JUAN", "zone": "  -  "}, {"region": "SAN JUAN", "area": "SAN JUAN", "zone": "ALTURAS DEL BOSQUE"}, {"region": "SAN JUAN", "area": "SAN JUAN", "zone": "Ave. 65 De Infanteria"}, {"region": "SAN JUAN", "area": "SAN JUAN", "zone": "BO LAS LOMAS SAB LLANA SUR"}, {"region": "SAN JUAN", "area": "SAN JUAN", "zone": "Bda. Buena Vista H.Re"}, {"region": "SAN JUAN", "area": "SAN JUAN", "zone": "Bda. Israel HR"}, {"region": "SAN JUAN", "area": "SAN JUAN", "zone": "CAM LOS ROMERO BO CAIMITO"}, {"region": "SAN JUAN", "area": "SAN JUAN", "zone": "DOCTOR JULIA CUPEY ALTO"}, {"region": "SAN JUAN", "area": "SAN JUAN", "zone": "GOBERNADOR PI\u00d1ERO"}, {"region": "SAN JUAN", "area": "SAN JUAN", "zone": "HATO REY CENTRAL"}, {"region": "SAN JUAN", "area": "SAN JUAN", "zone": "MONACILLO URBANO"}, {"region": "SAN JUAN", "area": "SAN JUAN", "zone": "ORIENTE"}, {"region": "SAN JUAN", "area": "SAN JUAN", "zone": "RES JARDINES DE CAMPO RICO"}, {"region": "SAN JUAN", "area": "SAN JUAN", "zone": "SABANA LLANA NORTE"}, {"region": "SAN JUAN", "area": "SAN JUAN", "zone": "URB ALTAMESA"}, {"region": "SAN JUAN", "area": "SAN JUAN", "zone": "URB MONTECARLO"}, {"region": "SAN JUAN", "area": "SAN JUAN", "zone": "URB SAGRADO CORAZON"}, {"region": "SAN JUAN", "area": "SAN JUAN", "zone": "URB SAN FRANCISCO"}, {"region": "SAN JUAN", "area": "SAN JUAN", "zone": "URB SAN JOSE"}, {"region": "SAN JUAN", "area": "SAN JUAN", "zone": "URB UNIV GARDENS"}, {"region": "SAN JUAN", "area": "SAN JUAN", "zone": "Urb. Caparra Terrace SE"}, {"region": "SAN JUAN", "area": "SAN JUAN", "zone": "Urb. Purple Tree"}, {"region": "SAN JUAN", "area": "SAN JUAN", "zone": "Viejo San Juan"}, {"region": "GUANICA", "area": "GUANICA", "zone": "ESTANCIAS MARIA ANTONIA"}, {"region": "GUANICA", "area": "GUANICA", "zone": "LA JOYA SECTOR LAS LATAS"}, {"region": "GUANICA", "area": "GUANICA", "zone": "URB VALLE TANIA"}, {"region": "CAGUAS", "area": "CAGUAS", "zone": "/CONT ENCERRADO/"}, {"region": "CAGUAS", "area": "CAGUAS", "zone": "BO BEATRIZ/SECTOR LAS ABEJAS"}, {"region": "CAGUAS", "area": "CAGUAS", "zone": "BO SAN ANTONIO"}, {"region": "CAGUAS", "area": "CAGUAS", "zone": "BO TOMAS DE CASTRO 2"}, {"region": "CAGUAS", "area": "CAGUAS", "zone": "BO TOMAS DE CASTRO II"}, {"region": "CAGUAS", "area": "CAGUAS", "zone": "CAGUAS"}, {"region": "CAGUAS", "area": "CAGUAS", "zone": "CA\u00d1ABONCITO"}, {"region": "CAGUAS", "area": "CAGUAS", "zone": "Casco Urbano Caguas"}, {"region": "CAGUAS", "area": "CAGUAS", "zone": "LAKE VIEW ESTATES"}, {"region": "CAGUAS", "area": "CAGUAS", "zone": "RIO CA\u00d1AS"}, {"region": "CAGUAS", "area": "CAGUAS", "zone": "SAN ANTONIO//CALLE ALEJANDRINO"}, {"region": "CAGUAS", "area": "CAGUAS", "zone": "SAN SALVADOR"}, {"region": "CAGUAS", "area": "CAGUAS", "zone": "TURABO ARRIBA,SOBACO,CANABONCI"}, {"region": "CAGUAS", "area": "CAGUAS", "zone": "URB BRISAS DE PARQUE"}, {"region": "CAGUAS", "area": "CAGUAS", "zone": "URB LAKEVIEW STATES"}, {"region": "CAGUAS", "area": "CAGUAS", "zone": "URB SAN ALFONSO/LOCAL 1"}, {"region": "CAGUAS", "area": "CAGUAS", "zone": "URB TURABO GARDENS 5TA"}, {"region": "CAGUAS", "area": "CAGUAS", "zone": "URB VILLA BLANCA"}, {"region": "CAGUAS", "area": "CAGUAS", "zone": "Urb. Notre Dame"}, {"region": "CAGUAS", "area": "CAGUAS", "zone": "VALLE SAN LUIS"}, {"region": "NARANJITO", "area": "NARANJITO", "zone": "ACHIOTE"}, {"region": "NARANJITO", "area": "NARANJITO", "zone": "Bo. Anones"}, {"region": "NARANJITO", "area": "NARANJITO", "zone": "Bo. Guadiana"}, {"region": "VEGA BAJA", "area": "VEGA BAJA", "zone": "Bo. Almirante Sur"}, {"region": "SAN LORENZO", "area": "SAN LORENZO", "zone": "BO ESPINO"}, {"region": "SAN LORENZO", "area": "SAN LORENZO", "zone": "BO QDA ARENAS, CAMINO WISO GOM"}, {"region": "SAN LORENZO", "area": "SAN LORENZO", "zone": "BO QUEMADO"}, {"region": "SAN LORENZO", "area": "SAN LORENZO", "zone": "Bo. Espino"}, {"region": "SAN LORENZO", "area": "SAN LORENZO", "zone": "PARC BLANCA BLANCO"}, {"region": "MAYAGUEZ", "area": "MAYAGUEZ", "zone": "APT 4A P4 COND DOMENECH"}, {"region": "MAYAGUEZ", "area": "MAYAGUEZ", "zone": "CALLEJON BOTOYO"}, {"region": "MAYAGUEZ", "area": "MAYAGUEZ", "zone": "MIRADERO"}, {"region": "MAYAGUEZ", "area": "MAYAGUEZ", "zone": "SECTOR CAMBALACHE BO LIMON"}, {"region": "MAYAGUEZ", "area": "MAYAGUEZ", "zone": "SECTOR LA CEIBA"}, {"region": "MAUNABO", "area": "MAUNABO", "zone": "BO LIZAS  /SECTOR LOS QUIROS"}, {"region": "MAUNABO", "area": "MAUNABO", "zone": "BO MATUYAS"}, {"region": "YAUCO", "area": "YAUCO", "zone": "BO FRAILES LOS BERROCALES"}, {"region": "YAUCO", "area": "YAUCO", "zone": "BO RANCHERAS/SECTOR COLLADO"}]