[{"region": "COROZAL", "area": "COROZAL", "zone": "BO PALOS BLANCOS NE-584"}, {"region": "CIALES", "area": "CIALES", "zone": "Bo. Pesas"}, {"region": "PATILLAS", "area": "PATILLAS", "zone": "BO MULAS"}, {"region": "PATILLAS", "area": "PATILLAS", "zone": "BO QUEBRADA ARRIBA"}, {"region": "PATILLAS", "area": "PATILLAS", "zone": "BO REAL SECTOR LAS PARCELAS"}, {"region": "BARCELONETA", "area": "BARCELONETA", "zone": "Bo. Palenque"}, {"region": "HUMACAO", "area": "HUMACAO", "zone": "BDA PRRA                 26028"}, {"region": "CIDRA", "area": "CIDRA", "zone": "Bo. Bayamon"}, {"region": "YABUCOA", "area": "YABUCOA", "zone": "CAMINO NUEVO"}, {"region": "TOA ALTA", "area": "TOA ALTA", "zone": "ORTIZ"}, {"region": "SABANA GRANDE", "area": "SABANA GRANDE", "zone": "Bo. Rincon Pozo"}, {"region": "SAN SEBASTIAN", "area": "SAN SEBASTIAN", "zone": "HATO ARRIBA"}, {"region": "CULEBRA", "area": "CULEBRA", "zone": "PLAYA SARDINAS I"}, {"region": "QUEBRADILLAS", "area": "QUEBRADILLAS", "zone": "TERRANOVA"}, {"region": "CAROLINA", "area": "CAROLINA", "zone": "URB METROPOLIS"}, {"region": "CAROLINA", "area": "CAROLINA", "zone": "Urb. Mountain View"}, {"region": "BARRANQUITAS", "area": "BARRANQUITAS", "zone": "BO QUEBRADA GRANDE"}, {"region": "TOA BAJA", "area": "TOA BAJA", "zone": "SABANA SECA"}, {"region": "TOA BAJA", "area": "TOA BAJA", "zone": "VILLA ALBIZU CANDELARIA"}, {"region": "BAYAMON", "area": "BAYAMON", "zone": "Bo. Hato Tejas"}, {"region": "BAYAMON", "area": "BAYAMON", "zone": "CERRO GORDO"}, {"region": "BAYAMON", "area": "BAYAMON", "zone": "ESTANCIAS DE RIO HONDO"}, {"region": "LAS PIEDRAS", "area": "LAS PIEDRAS", "zone": "LAS PIEDRAS"}, {"region": "PONCE", "area": "PONCE", "zone": "RES EL PARAISO LA YUCA"}, {"region": "PONCE", "area": "PONCE", "zone": "URB. MONTES LLANOS"}, {"region": "UTUADO", "area": "UTUADO", "zone": "BO CAONILLAS"}, {"region": "UTUADO", "area": "UTUADO", "zone": "Bo. Mameyes Arriba"}, {"region": "UTUADO", "area": "UTUADO", "zone": "MAMEYES ABAJO"}, {"region": "UTUADO", "area": "UTUADO", "zone": "VIVI ABAJO ALTURAS DE UTUADO"}, {"region": "NAGUABO", "area": "NAGUABO", "zone": "NAGUABO"}, {"region": "SAN JUAN", "area": "SAN JUAN", "zone": "Urb. Monte Hiedra"}, {"region": "CAGUAS", "area": "CAGUAS", "zone": "URB VILLA NUEVA"}, {"region": "VEGA BAJA", "area": "VEGA BAJA", "zone": "ALMIRANTE NORTE"}, {"region": "SAN LORENZO", "area": "SAN LORENZO", "zone": "ESTANCIAS DE SAN LORENZO"}]