[{"region": "CIALES", "area": "CIALES", "zone": "BO CORDILLERA"}, {"region": "BARCELONETA", "area": "BARCELONETA", "zone": "PAR PUNTA PALMA 51"}, {"region": "ANASCO", "area": "ANASCO", "zone": "HUMATAS"}, {"region": "ISABELA", "area": "ISABELA", "zone": "URB COSTA BRAVA"}, {"region": "SAN SEBASTIAN", "area": "SAN SEBASTIAN", "zone": "ALTOSANO / CAJAS DE AGUA/MOLIN"}, {"region": "GUAYNABO", "area": "GUAYNABO", "zone": "Urb. Colimar"}, {"region": "JUNCOS", "area": "JUNCOS", "zone": "CEIBA NORTE"}, {"region": "BARRANQUITAS", "area": "BARRANQUITAS", "zone": "BO BARRANCAS"}, {"region": "NAGUABO", "area": "NAGUABO", "zone": "PE\u00acA POBRE MEDIANIA RL 135"}, {"region": "SAN JUAN", "area": "SAN JUAN", "zone": "Urb. Highland Park"}, {"region": "CAGUAS", "area": "CAGUAS", "zone": "CAGUAS"}, {"region": "SAN LORENZO", "area": "SAN LORENZO", "zone": "BO QUEMADO/ENTRADA LOS ADORNOS"}]