[{"region": "COROZAL", "area": "COROZAL", "zone": "Bo. Padilla"}, {"region": "COROZAL", "area": "COROZAL", "zone": "URB LOMAS LINDA"}, {"region": "LOIZA", "area": "LOIZA", "zone": "LOIZA"}, {"region": "ANASCO", "area": "ANASCO", "zone": "BO CERRO GORDO"}, {"region": "ISABELA", "area": "ISABELA", "zone": "ISLA BELA BEACH RESORT"}, {"region": "AGUADILLA", "area": "AGUADILLA", "zone": "Bo. Borinquen"}, {"region": "GUAYNABO", "area": "GUAYNABO", "zone": "SANTA ROSA"}, {"region": "GUAYNABO", "area": "GUAYNABO", "zone": "URB LAS RAMBLAS III"}, {"region": "CAROLINA", "area": "CAROLINA", "zone": "BO BARRAZAS"}, {"region": "BAYAMON", "area": "BAYAMON", "zone": "Bo. Hato Tejas"}, {"region": "COAMO", "area": "COAMO", "zone": "URB CARMEN FAS BO STA CATALINA"}, {"region": "SAN JUAN", "area": "SAN JUAN", "zone": "PUERTO NUEVO"}, {"region": "SAN JUAN", "area": "SAN JUAN", "zone": "URB FAIR VIEW"}]